{"ru": {}, "ar": {}, "en": {"CA": 37625, "US": 1115117, "GB": 224396, "PE": 456, "JP": 3272, "AU": 20975, "PK": 5695, "AG": 777, "IE": 11944, "MY": 31722, "MX": 5782, "ID": 21949, "IN": 31098, "TH": 9559, "JM": 1412, "GH": 5231, "ES": 11973, "GR": 2731, "PH": 50118, "NZ": 3232, "IT": 4573, "EC": 747, "ZA": 32278, "UA": 473, "HK": 652, "DO": 579, "GU": 1265, "PT": 3067, "NG": 15576, "KE": 4983, "SE": 2943, "IS": 268, "UG": 1375, "BR": 15741, "KW": 4733, "KR": 1391, "EG": 1730, "NL": 5487, "MT": 274, "CO": 819, "AR": 2534, "BS": 962, "GT": 237, "BE": 3218, "LB": 1144, "DK": 1288, "IQ": 235, "CY": 811, "VN": 514, "AE": 6915, "TZ": 573, "FI": 702, "SI": 317, "SG": 8504, "SA": 2910, "DE": 7106, "TR": 8237, "BW": 794, "CR": 487, "CN": 803, "PL": 1534, "RO": 770, "BD": 647, "BB": 737, "MP": 449, "HN": 169, "NI": 194, "BA": 339, "QA": 1013, "VE": 488, "NA": 612, "PY": 184, "RU": 1263, "TT": 929, "CL": 531, "FR": 8481, "HR": 656, "CZ": 780, "ME": 151, "HU": 367, "BG": 545, "MA": 460, "IL": 997, "ZW": 864, "LV": 181, "LK": 713, "CH": 834, "BN": 665, "KH": 260, "AT": 1041, "LC": 236, "BH": 659, "NP": 545, "TW": 168, "JO": 970, "OM": 609, "PA": 340, "MV": 242, "NO": 1040, "MW": 151, "SK": 374, "RW": 233, "BY": 154, "IM": 220, "EE": 283, "SD": 336, "HT": 275, "MU": 175, "VC": 273, "ZM": 378, "TC": 240, "XK": 303, "LS": 146, "KY": 154, "DZ": 284, "LY": 149, "TN": 372, "AL": 175, "BM": 233, "VG": 405, "nogeo": 1439925}, "es": {"AR": 358560, "CL": 44247, "MX": 132144, "ES": 141961, "CR": 7606, "CO": 64249, "VE": 49193, "DO": 6860, "PE": 15747, "UY": 40605, "BR": 29288, "GT": 6303, "US": 46817, "PY": 9531, "HN": 2105, "EC": 11202, "PA": 5651, "NI": 4145, "PT": 2498, "SV": 1827, "CA": 983, "DE": 447, "RO": 418, "IL": 539, "BO": 810, "FR": 662, "IT": 512, "PH": 344, "GB": 332, "AT": 254, "IE": 248, "TR": 662, "nogeo": 2049157}}