{"ru": {}, "ar": {"SA": 69357, "BH": 4278, "US": 1053, "EG": 21055, "AE": 10505, "KW": 17657, "YE": 617, "QA": 5941, "OM": 3692, "LY": 2240, "JO": 2006, "GB": 981, "IQ": 2974, "CA": 298, "DZ": 844, "LB": 2310, "TR": 608, "SD": 1179, "TN": 600, "NL": 241, "nogeo": 2302957}, "en": {"US": 1457957, "SG": 6083, "CA": 65728, "SA": 3380, "MX": 7190, "AU": 26095, "GB": 214771, "MY": 20917, "KE": 6164, "BR": 20507, "PH": 56950, "IN": 49750, "HK": 1104, "TW": 260, "JP": 4315, "DE": 10860, "PT": 4637, "ID": 9255, "AR": 3204, "TT": 1457, "IE": 14832, "AT": 902, "PK": 4946, "VC": 209, "GR": 819, "NZ": 4400, "CO": 1810, "IS": 561, "BS": 902, "CH": 1290, "CL": 945, "LC": 430, "": 279, "AE": 6009, "IT": 3987, "NO": 831, "KR": 2006, "GT": 268, "NG": 19879, "DO": 550, "BB": 843, "FR": 6958, "ZA": 40387, "GH": 4744, "CN": 1139, "NP": 522, "BG": 378, "ES": 8240, "IL": 1731, "EG": 1718, "JM": 1939, "TH": 4073, "SE": 2442, "VN": 624, "NL": 6623, "NI": 274, "BN": 392, "FI": 876, "KW": 4422, "CR": 566, "ZM": 684, "UG": 1370, "BW": 825, "DK": 1327, "BE": 3332, "CZ": 1111, "HR": 349, "RU": 1075, "TR": 3388, "QA": 1171, "LK": 911, "OM": 484, "MW": 250, "SD": 341, "CI": 288, "TZ": 655, "BH": 766, "IQ": 278, "PL": 1303, "JO": 370, "VE": 475, "ZW": 722, "EE": 204, "RO": 483, "GU": 721, "LV": 192, "AG": 553, "MM": 198, "RW": 300, "HU": 475, "KH": 176, "NA": 632, "BD": 1041, "UY": 256, "MV": 280, "LY": 198, "CY": 507, "IM": 211, "PE": 1096, "LB": 1007, "PA": 276, "MT": 183, "LU": 252, "EC": 180, "SN": 241, "XK": 232, "SK": 185, "MP": 240, "UA": 480, "SI": 203, "HT": 181, "RS": 169, "PY": 185, "TC": 293, "nogeo": 1652419}, "es": {"HN": 1255, "BR": 16775, "AR": 146612, "MX": 96348, "CL": 33533, "UY": 20824, "VE": 26424, "DO": 5655, "CO": 44115, "GT": 4304, "US": 26558, "PY": 7376, "EC": 9826, "PA": 3868, "NI": 2962, "JP": 211, "ES": 97697, "CR": 6262, "PE": 9891, "BO": 921, "SV": 1398, "CA": 527, "PT": 644, "PH": 259, "FR": 350, "PR": 257, "CU": 267, "IT": 530, "BE": 284, "IL": 340, "nogeo": 1732508}}