{"ru": {}, "ar": {"SA": 4769, "KW": 1135, "EG": 844, "BH": 326, "AE": 280, "nogeo": 2542407}, "en": {"US": 1266022, "CA": 63529, "PH": 60061, "AU": 28812, "GB": 217687, "AR": 3340, "MY": 24338, "PE": 1040, "BR": 22949, "PT": 3017, "PY": 241, "ID": 15937, "TT": 1024, "NZ": 4697, "AE": 5895, "ZA": 29045, "IN": 39110, "NG": 21343, "KR": 1487, "CN": 1352, "BD": 655, "KE": 5283, "TH": 5914, "JM": 2122, "PA": 276, "MX": 6803, "SG": 7026, "VE": 1029, "EG": 1684, "NL": 5840, "TW": 609, "CH": 1194, "BB": 803, "IE": 12953, "GH": 4017, "DE": 7904, "BS": 734, "IS": 629, "UG": 1173, "KW": 6159, "ES": 8350, "JP": 5060, "BN": 459, "GU": 508, "PK": 5261, "FR": 7360, "IL": 1492, "HU": 484, "HK": 2101, "CO": 1365, "IM": 199, "DK": 1331, "CR": 587, "VN": 508, "AG": 448, "SA": 3159, "HR": 485, "FI": 812, "QA": 1054, "GR": 924, "SE": 1978, "NA": 566, "LK": 714, "KH": 262, "BH": 809, "TR": 6680, "OM": 434, "SD": 411, "PL": 1246, "IT": 4403, "LB": 652, "TZ": 375, "EC": 464, "SK": 187, "DO": 786, "BE": 2934, "NO": 1099, "BW": 1062, "CL": 913, "MV": 532, "RO": 567, "MT": 245, "RU": 914, "NP": 485, "UY": 232, "ZM": 390, "CY": 602, "UA": 704, "JO": 282, "GI": 196, "GE": 660, "NI": 183, "BG": 362, "AT": 520, "HT": 188, "RW": 186, "ZW": 395, "MW": 206, "CZ": 393, "DZ": 353, "nogeo": 1828338}, "es": {"AR": 127674, "ES": 84963, "VE": 45124, "CL": 33258, "MX": 83925, "UY": 17458, "CO": 38008, "PE": 9813, "PY": 6397, "GT": 3853, "BR": 15438, "SV": 1698, "US": 23951, "EC": 8000, "CR": 5364, "PA": 3885, "CU": 306, "DO": 4572, "FR": 465, "BO": 732, "CA": 367, "NI": 2079, "HN": 904, "PH": 500, "IT": 563, "IL": 385, "PT": 635, "DE": 368, "TR": 536, "nogeo": 1687290}}