{"ru": {}, "ar": {"SA": 5511, "AE": 687, "BH": 392, "EG": 884, "KW": 921, "nogeo": 2584191}, "en": {"US": 1426371, "IN": 35755, "IE": 12837, "BR": 26498, "CA": 58366, "PH": 68268, "MY": 30168, "DE": 8408, "CL": 1114, "GH": 3228, "GB": 223008, "CN": 1397, "HK": 988, "JM": 2630, "ID": 21889, "KW": 5485, "AR": 4846, "PT": 3651, "MX": 8063, "IM": 283, "NZ": 4239, "SG": 8353, "AU": 28366, "VN": 278, "FR": 9370, "TT": 1060, "ES": 9125, "PK": 5812, "CO": 2019, "NG": 27279, "KR": 2442, "SE": 4040, "EG": 2177, "TW": 329, "BD": 683, "CR": 1030, "HR": 331, "ZA": 34062, "NL": 5880, "BS": 1019, "GU": 819, "VE": 687, "AE": 6430, "GT": 270, "KY": 237, "TH": 6999, "JP": 4732, "CZ": 411, "PL": 1757, "HT": 209, "IT": 4388, "BN": 430, "KE": 4672, "BE": 3354, "NI": 222, "SA": 3497, "GR": 1306, "BB": 1175, "DK": 1729, "FI": 553, "IL": 1021, "RU": 1089, "QA": 1735, "BH": 783, "TR": 7319, "SN": 208, "LK": 1092, "ZM": 500, "DZ": 624, "BW": 1057, "PA": 377, "UG": 867, "IS": 434, "AG": 599, "ZW": 642, "BG": 419, "RO": 621, "AT": 817, "LC": 191, "SD": 365, "NA": 940, "KH": 581, "OM": 522, "PE": 887, "MV": 257, "JO": 441, "KZ": 406, "DO": 471, "TZ": 337, "MA": 192, "LB": 911, "KP": 222, "CY": 391, "NP": 674, "HU": 481, "": 216, "EC": 229, "UY": 518, "UA": 561, "SI": 232, "SK": 440, "CH": 1043, "HN": 223, "LU": 205, "NO": 495, "MT": 189, "BY": 197, "XK": 209, "TN": 208, "BA": 223, "nogeo": 1880159}, "es": {"MX": 88703, "AR": 164814, "CO": 47904, "CL": 33340, "VE": 36419, "EC": 20247, "US": 26042, "UY": 24969, "PY": 6358, "BR": 22513, "PE": 10046, "GT": 3401, "ES": 105041, "PA": 4022, "BO": 748, "DO": 4888, "CA": 338, "CR": 5680, "HN": 1272, "NI": 2205, "CU": 246, "SV": 1277, "PH": 642, "FR": 395, "PT": 933, "DE": 519, "IL": 381, "IT": 583, "nogeo": 1876332}}