{"ru": {}, "ar": {"SA": 5666, "AE": 778, "EG": 1016, "BH": 364, "KW": 1199, "nogeo": 2611437}, "en": {"US": 1540354, "BR": 24968, "GB": 248513, "NG": 27107, "PH": 76064, "BB": 1189, "IN": 38088, "IE": 15522, "CA": 71240, "AU": 29710, "HK": 1472, "ES": 10833, "EC": 244, "VE": 765, "MY": 29119, "TH": 6548, "NZ": 4075, "ID": 22752, "JM": 2563, "MX": 9956, "CO": 2513, "DE": 8982, "PT": 3245, "FR": 9602, "BS": 870, "CL": 2028, "UY": 565, "CZ": 663, "SA": 3730, "DK": 1407, "EG": 2291, "RU": 1215, "SD": 441, "CR": 853, "AE": 7762, "KE": 4786, "AR": 5657, "PE": 1614, "PL": 1424, "IT": 5401, "JP": 4177, "KH": 538, "TW": 325, "SG": 8562, "KR": 1290, "TT": 1798, "SE": 2877, "GH": 3755, "ZA": 32195, "PK": 5476, "TR": 6561, "BE": 3618, "NP": 803, "GU": 759, "UG": 678, "GT": 374, "NL": 6264, "CN": 1284, "QA": 1122, "GR": 1069, "JO": 375, "FI": 793, "ZM": 493, "KZ": 756, "IL": 919, "KW": 7480, "BN": 458, "MV": 382, "BG": 425, "BH": 984, "RO": 682, "LK": 825, "NI": 388, "BD": 1250, "PY": 485, "OM": 570, "GE": 196, "HR": 313, "LB": 1073, "BW": 1296, "NO": 848, "ZW": 431, "DO": 473, "NA": 620, "AT": 670, "CH": 885, "TN": 301, "HU": 488, "CY": 571, "TZ": 423, "DZ": 475, "IM": 405, "HN": 243, "HT": 242, "SK": 402, "PA": 266, "VN": 290, "SI": 199, "IS": 434, "AG": 328, "UA": 583, "XK": 222, "nogeo": 1888114}, "es": {"VE": 34929, "MX": 100624, "AR": 163864, "CL": 58352, "CO": 49913, "PY": 7812, "SV": 1455, "PE": 14507, "US": 31043, "EC": 9434, "ES": 107305, "GT": 4379, "NI": 2893, "BR": 18554, "CR": 6845, "UY": 26099, "PT": 937, "HN": 1683, "CA": 771, "PA": 2907, "DO": 5228, "BO": 1102, "CU": 211, "FR": 522, "AT": 220, "PH": 742, "IL": 318, "IT": 694, "PR": 206, "TR": 526, "NL": 221, "GB": 201, "nogeo": 1920524}}