{"ru": {}, "ar": {"BH": 3472, "SA": 74762, "US": 678, "EG": 19773, "LB": 1567, "OM": 2734, "QA": 6805, "KW": 15275, "YE": 421, "SD": 1022, "AE": 9353, "LY": 2592, "TN": 297, "DZ": 1012, "JO": 2178, "IQ": 1877, "TR": 276, "nogeo": 2502374}, "en": {"CA": 61221, "GB": 358789, "US": 1365216, "PH": 55883, "MX": 8184, "BR": 25422, "QA": 1027, "PL": 1511, "NZ": 3853, "AU": 29297, "ES": 11320, "SG": 6727, "FR": 11032, "IN": 38817, "GT": 320, "ID": 15105, "MY": 22936, "KR": 1551, "KW": 4787, "IE": 17248, "PK": 4866, "CH": 1762, "AG": 608, "AE": 5714, "ZA": 33765, "NG": 17337, "AR": 3756, "DE": 9719, "JM": 1740, "IT": 5330, "TT": 1347, "SE": 3515, "TR": 10174, "BS": 1387, "BH": 701, "PA": 444, "VE": 565, "GR": 2205, "JP": 4828, "BE": 3845, "HU": 909, "MU": 358, "NL": 7659, "": 311, "BG": 704, "IM": 380, "TH": 4536, "CR": 996, "CO": 1842, "EG": 1446, "BM": 215, "HK": 1373, "UY": 508, "CN": 2045, "BB": 906, "RU": 2515, "GE": 369, "CL": 837, "FI": 872, "GI": 235, "BW": 1070, "DO": 648, "NP": 662, "DK": 1653, "AM": 233, "PE": 1011, "PT": 3654, "IL": 1438, "KE": 5513, "JO": 377, "LB": 982, "CY": 764, "KH": 217, "AT": 894, "ZM": 513, "IQ": 211, "LK": 1331, "GH": 3980, "MM": 178, "UG": 1288, "LY": 181, "EC": 194, "HT": 231, "SA": 3346, "NA": 480, "CZ": 1092, "SK": 261, "IR": 236, "ZW": 490, "KZ": 609, "BD": 876, "TZ": 639, "GU": 668, "RO": 615, "MV": 241, "BY": 192, "VN": 403, "BN": 355, "RW": 228, "HR": 615, "IS": 497, "NO": 617, "UA": 844, "BA": 216, "OM": 411, "TW": 284, "LC": 289, "MW": 305, "TN": 459, "NI": 301, "EE": 204, "MT": 252, "SD": 298, "MC": 276, "RS": 186, "PY": 213, "VG": 245, "LU": 236, "XK": 221, "KY": 184, "nogeo": 1706837}, "es": {"AR": 137364, "CL": 30744, "PA": 4581, "MX": 89382, "UY": 23150, "PE": 9918, "CO": 44819, "CR": 7254, "US": 27730, "PT": 704, "ES": 91326, "VE": 40281, "BR": 17106, "PY": 6218, "NI": 1844, "EC": 8631, "DO": 4771, "GT": 3215, "SV": 1357, "CA": 715, "GB": 222, "HN": 1480, "CU": 242, "BO": 731, "DE": 466, "IT": 669, "PH": 472, "FR": 858, "IL": 297, "RO": 175, "BE": 178, "nogeo": 1726794}}