{"ru": {}, "ar": {"SA": 69961, "GB": 317, "EG": 19853, "KW": 17207, "OM": 3143, "AE": 10284, "US": 1794, "LY": 1767, "BH": 4047, "QA": 5006, "JO": 1832, "TR": 352, "YE": 505, "LB": 1572, "CA": 220, "IQ": 2183, "SD": 795, "DZ": 532, "TN": 348, "SY": 550, "nogeo": 2148441}, "en": {"US": 1293396, "AU": 30599, "CA": 54138, "GB": 188472, "SG": 6082, "TT": 1785, "PH": 50610, "BR": 18300, "NL": 6233, "IN": 40175, "ID": 8839, "CO": 1416, "NZ": 4164, "MX": 6184, "TR": 3242, "JM": 1982, "PK": 5065, "ZA": 34382, "MY": 18846, "LC": 275, "LU": 307, "CL": 1083, "IE": 14897, "PL": 1341, "JP": 4239, "NG": 18118, "UA": 412, "DE": 9435, "ES": 8760, "VC": 267, "HK": 946, "NI": 277, "AG": 293, "GH": 4275, "VN": 543, "KE": 6129, "BH": 685, "TH": 3507, "BB": 679, "CN": 1178, "FR": 6748, "KR": 983, "JO": 291, "AR": 2762, "RU": 1196, "HN": 201, "AE": 5722, "BS": 794, "GR": 1035, "XK": 242, "CH": 1129, "SA": 3034, "IT": 4071, "BE": 3036, "TZ": 433, "SE": 2225, "PE": 797, "SN": 176, "DK": 1412, "MT": 252, "QA": 1532, "FI": 729, "CZ": 926, "IL": 1160, "LB": 789, "RO": 677, "BW": 633, "GT": 200, "AT": 862, "PA": 375, "CY": 570, "KW": 4227, "HU": 587, "BD": 805, "NP": 481, "GU": 593, "EC": 165, "MM": 171, "UG": 1216, "TW": 260, "LV": 183, "BN": 400, "EG": 1513, "SD": 306, "LK": 757, "OM": 428, "ZW": 521, "CR": 566, "BG": 405, "NA": 584, "MU": 189, "MV": 251, "RW": 195, "UY": 264, "": 249, "PT": 2301, "ZM": 546, "KH": 187, "MW": 214, "NO": 553, "IQ": 187, "SK": 177, "DO": 227, "VE": 530, "RS": 173, "HR": 265, "HT": 203, "PY": 201, "IS": 383, "nogeo": 1545245}, "es": {"AR": 172558, "MX": 93123, "EC": 13430, "GT": 4490, "VE": 26399, "UY": 24099, "CO": 64236, "CL": 51043, "PE": 16939, "ES": 98776, "PY": 12883, "HN": 3208, "BR": 18065, "PA": 8635, "CR": 9696, "US": 26933, "SV": 1669, "DO": 4265, "CA": 1149, "RU": 251, "NI": 2846, "BO": 1175, "AU": 326, "PR": 222, "PT": 700, "IT": 650, "FR": 599, "PH": 228, "RO": 178, "IL": 246, "CU": 519, "DE": 415, "BE": 175, "GB": 181, "nogeo": 1533828}}