{"ru": {}, "ar": {"SA": 94525, "AE": 11859, "EG": 20734, "LY": 2168, "QA": 5847, "BH": 4535, "AU": 353, "SD": 1564, "KW": 19654, "OM": 5108, "US": 1789, "GB": 1017, "LB": 1675, "IQ": 2143, "JO": 1590, "YE": 552, "TR": 584, "IR": 293, "DZ": 402, "SY": 335, "nogeo": 2035872}, "en": {"US": 1301167, "GB": 205906, "AE": 5939, "PK": 5931, "BB": 795, "PH": 43501, "FR": 5673, "SG": 5519, "CA": 55388, "KE": 5399, "BR": 14080, "DE": 6609, "ES": 6948, "NG": 22214, "MX": 6553, "AU": 28940, "ID": 6886, "TR": 2738, "LY": 235, "RU": 1108, "IE": 13244, "NZ": 3985, "MY": 15860, "UG": 1179, "TT": 1577, "JM": 2339, "NL": 5680, "IN": 38098, "PE": 498, "JP": 3143, "HK": 758, "BH": 761, "NP": 588, "TW": 232, "EC": 202, "VG": 412, "CI": 218, "ZA": 43460, "MV": 465, "GR": 515, "BS": 1201, "GH": 8084, "CY": 535, "CN": 1349, "PT": 1686, "CO": 1206, "TH": 2739, "LC": 543, "NI": 236, "CR": 614, "LK": 941, "BN": 286, "DO": 391, "": 557, "AR": 2518, "IT": 3502, "KR": 1491, "MW": 354, "HU": 429, "FI": 559, "ZM": 1086, "DK": 806, "SE": 1778, "IS": 327, "SA": 3496, "BE": 2933, "NA": 932, "ZW": 1274, "BD": 691, "KW": 4545, "QA": 835, "LB": 609, "EG": 1318, "TZ": 671, "GU": 554, "BW": 695, "MT": 191, "AT": 516, "IL": 810, "KH": 245, "GT": 190, "CZ": 392, "RW": 224, "AF": 163, "MU": 239, "MM": 160, "JO": 215, "TC": 282, "HT": 283, "UY": 174, "CL": 680, "SN": 164, "NO": 491, "SI": 173, "IQ": 254, "UA": 579, "CH": 1193, "PA": 304, "RS": 185, "VN": 416, "OM": 469, "RO": 275, "BG": 247, "BY": 183, "KY": 162, "PL": 672, "SD": 336, "IM": 200, "LS": 214, "HR": 214, "AG": 310, "BM": 170, "XK": 170, "GM": 165, "nogeo": 1599033}, "es": {"US": 28411, "CL": 30717, "AR": 119773, "MX": 79095, "CO": 39496, "PE": 7336, "UY": 14340, "CR": 5878, "GT": 3279, "ES": 72469, "BR": 15207, "VE": 11398, "DO": 3817, "PY": 5412, "EC": 7257, "FR": 335, "SV": 1192, "NI": 2101, "PA": 4427, "HN": 1008, "BO": 780, "CA": 452, "PH": 229, "ZA": 168, "IT": 474, "IL": 164, "CH": 201, "PT": 574, "nogeo": 1616202}}