{"ru": {}, "ar": {"EG": 26954, "SA": 92673, "AE": 10764, "KW": 19231, "OM": 6487, "SD": 1920, "LY": 3610, "BH": 4200, "US": 1630, "GB": 449, "TN": 349, "QA": 4249, "JP": 1265, "DE": 619, "JO": 2588, "IQ": 2994, "TR": 1439, "LB": 2403, "CA": 447, "RU": 299, "IR": 237, "SY": 274, "YE": 472, "FR": 297, "DZ": 262, "nogeo": 2071570}, "en": {"US": 1366410, "GB": 216887, "FI": 573, "PH": 44115, "AU": 25287, "CA": 60100, "EC": 342, "MY": 17802, "IN": 39113, "SA": 4731, "MX": 7623, "UY": 208, "GH": 8401, "ID": 8171, "PT": 2266, "JM": 3553, "JP": 3455, "ZW": 1105, "AR": 2313, "UA": 857, "IE": 13769, "AL": 234, "BS": 1321, "TH": 3078, "NG": 28900, "QA": 988, "BR": 14692, "NZ": 3464, "HK": 811, "RU": 3812, "NL": 6251, "SG": 4831, "IT": 4343, "TR": 4131, "TC": 265, "DZ": 388, "GU": 558, "KW": 4207, "IQ": 1474, "BM": 311, "CN": 1623, "AG": 609, "EG": 3023, "ZA": 47152, "DO": 473, "ES": 9481, "CL": 765, "PE": 493, "XK": 316, "NP": 706, "BB": 826, "TT": 1583, "DE": 9109, "HR": 748, "TN": 1202, "RS": 294, "UG": 1199, "SE": 2200, "GR": 2001, "AE": 6183, "DK": 1367, "FR": 6344, "KH": 227, "CY": 778, "BN": 264, "PK": 6179, "CH": 1458, "NO": 533, "PA": 407, "PL": 1019, "BH": 1119, "IL": 1066, "VC": 223, "IS": 364, "KE": 6116, "TZ": 498, "": 841, "KR": 1557, "ZM": 1012, "TW": 260, "VG": 238, "MV": 740, "LB": 1046, "MC": 161, "IM": 155, "BD": 871, "BE": 3085, "SK": 147, "CO": 844, "KG": 153, "SD": 310, "VE": 171, "LK": 820, "BW": 1122, "VN": 237, "NA": 912, "CR": 615, "JO": 335, "BA": 146, "LU": 146, "HN": 215, "MA": 504, "PY": 170, "KZ": 148, "AT": 759, "HU": 527, "RO": 220, "GT": 253, "RW": 272, "MU": 230, "LC": 589, "MM": 208, "OM": 716, "MW": 379, "HT": 368, "CZ": 481, "MP": 167, "SI": 190, "EE": 226, "MT": 266, "BG": 522, "SN": 328, "KY": 178, "LY": 232, "VI": 154, "SZ": 148, "GM": 191, "nogeo": 1447242}, "es": {"MX": 124574, "AR": 118448, "UY": 14211, "HN": 1790, "ES": 75684, "BR": 19283, "GT": 3776, "CL": 28909, "CO": 40020, "VE": 12363, "EC": 9043, "PE": 7301, "US": 44443, "DO": 3920, "PY": 5210, "SV": 1780, "NI": 2237, "CA": 1415, "PA": 4831, "CR": 7627, "BO": 799, "RU": 4301, "PT": 546, "ZA": 190, "PH": 366, "IT": 617, "NL": 171, "IL": 204, "FR": 326, "DE": 705, "GB": 179, "nogeo": 1512991}}