{"ru": {}, "ar": {"AE": 9307, "SA": 80361, "LY": 2714, "EG": 19359, "KW": 17548, "YE": 609, "OM": 5729, "US": 1851, "GB": 760, "BH": 4152, "LB": 2103, "TR": 562, "QA": 3776, "": 2024, "CA": 242, "JO": 1917, "IQ": 2494, "IR": 351, "SY": 222, "DZ": 252, "TN": 221, "nogeo": 2130299}, "en": {"US": 1285613, "PH": 43177, "CA": 53851, "AU": 27976, "GB": 187219, "BR": 11349, "SG": 4464, "MX": 4666, "IE": 13548, "NZ": 3588, "IN": 36910, "ID": 6856, "NG": 32527, "HT": 209, "CL": 823, "GH": 8123, "MY": 14995, "TH": 2155, "SA": 4057, "KH": 221, "VC": 344, "ZA": 41185, "JP": 3067, "GT": 173, "RU": 944, "JM": 2176, "AR": 2472, "LK": 1021, "UA": 517, "EG": 1536, "BN": 360, "KE": 5640, "ES": 8212, "NL": 5159, "TT": 1305, "UY": 228, "TC": 230, "DE": 8642, "CY": 609, "BD": 716, "CR": 357, "IT": 3632, "BS": 915, "CN": 1143, "PK": 5889, "CH": 1300, "KR": 1443, "AE": 5074, "PL": 635, "PE": 451, "XK": 155, "NP": 399, "GR": 996, "": 1562, "FR": 4432, "KW": 4163, "DK": 1151, "BE": 2819, "BH": 741, "HU": 436, "UG": 1435, "LU": 279, "NA": 944, "IL": 1241, "ZM": 1035, "NO": 392, "RW": 372, "CO": 832, "TR": 2455, "LB": 567, "BW": 1000, "SE": 1733, "ZW": 1439, "HK": 461, "AG": 392, "OM": 415, "HR": 341, "FI": 669, "VN": 212, "QA": 771, "CZ": 416, "HN": 203, "MW": 428, "MV": 632, "AT": 525, "TZ": 611, "MT": 226, "KY": 167, "PT": 1819, "MM": 230, "RO": 244, "BB": 617, "TW": 231, "BG": 193, "CM": 179, "LC": 224, "IQ": 201, "SZ": 167, "GU": 393, "IS": 326, "JO": 223, "LY": 189, "PA": 322, "VG": 243, "SN": 199, "DZ": 152, "CI": 171, "RS": 156, "BM": 204, "KN": 278, "nogeo": 1515102}, "es": {"US": 27467, "ES": 76523, "AR": 109627, "MX": 75274, "CA": 1067, "CL": 27024, "BR": 13618, "VE": 10651, "CO": 39507, "UY": 13558, "CR": 4412, "PY": 5816, "GT": 3393, "PE": 9331, "EC": 8241, "SV": 1727, "BO": 872, "PA": 4371, "AU": 153, "DO": 3658, "HN": 1358, "NI": 1662, "ZA": 203, "PH": 281, "IL": 193, "PT": 475, "IT": 796, "DE": 163, "FR": 342, "TR": 235, "BE": 176, "nogeo": 1510839}}