{"ru": {"RU": 30345, "MN": 1346, "US": 279, "KZ": 632, "UZ": 211, "KG": 384, "BY": 2132, "GE": 141, "BG": 161, "EE": 237, "UA": 4941, "CA": 204, "IL": 474, "CZ": 124, "DE": 107, "LV": 118, "nogeo": 994841}, "ar": {"SA": 111766, "OM": 8067, "AE": 8635, "KW": 19283, "EG": 24238, "US": 1393, "LB": 4527, "": 2586, "IQ": 4615, "CA": 280, "QA": 2077, "BH": 4648, "LY": 3477, "SY": 392, "AU": 265, "GB": 1000, "YE": 595, "JO": 3031, "TR": 807, "TN": 205, "DE": 370, "MA": 200, "DZ": 262, "nogeo": 1766415}, "en": {"CA": 43375, "US": 940221, "AU": 18961, "ID": 11777, "SG": 3658, "IN": 37729, "HT": 177, "PH": 48993, "MX": 3720, "BB": 799, "BR": 10803, "AR": 1572, "MY": 16534, "FR": 3414, "NZ": 2932, "GB": 169620, "TH": 2161, "NG": 51622, "JM": 3591, "JP": 3045, "SA": 4233, "": 3706, "TT": 1481, "KR": 1443, "DE": 5995, "CO": 759, "ES": 4664, "CY": 618, "MM": 155, "CN": 1009, "ZA": 42720, "SZ": 268, "IE": 10372, "CL": 523, "AE": 5297, "BO": 178, "HK": 1256, "PK": 5105, "LC": 509, "HN": 205, "BS": 1204, "KE": 6661, "IT": 1911, "AG": 372, "KY": 209, "NL": 4246, "UA": 440, "IL": 795, "MV": 364, "ZW": 843, "BE": 1585, "GH": 7981, "BW": 1433, "NA": 1506, "QA": 917, "UG": 2219, "PT": 1462, "SE": 1356, "NP": 470, "LK": 1316, "IS": 163, "OM": 493, "MW": 1003, "TW": 357, "KW": 2742, "ZM": 1027, "RU": 350, "VC": 193, "TZ": 802, "TR": 1553, "DK": 903, "GT": 176, "RW": 262, "BH": 631, "ET": 220, "HU": 351, "PL": 576, "AF": 175, "UY": 161, "PA": 490, "AT": 454, "PE": 300, "MU": 387, "LS": 239, "VN": 426, "LB": 829, "BD": 642, "EG": 952, "MZ": 237, "CZ": 369, "BN": 216, "FI": 335, "CM": 161, "GR": 329, "CD": 186, "CH": 670, "BG": 216, "HR": 176, "KH": 198, "JO": 217, "NO": 362, "EC": 152, "RO": 178, "GU": 196, "VG": 169, "CR": 187, "IQ": 381, "XK": 504, "SK": 158, "MT": 225, "SN": 301, "DM": 155, "IM": 163, "BM": 249, "nogeo": 1510925}, "es": {"CO": 43430, "MX": 68788, "ES": 75611, "BO": 2271, "UY": 15021, "US": 23933, "AR": 89872, "BR": 16886, "PY": 5625, "CL": 39095, "VE": 10484, "EC": 8537, "HN": 2303, "PA": 5945, "CR": 2683, "GT": 3016, "DO": 4929, "PE": 9677, "CA": 1246, "NI": 1734, "PT": 465, "": 738, "SV": 1935, "CU": 259, "PH": 787, "ID": 167, "DE": 322, "IT": 464, "ZA": 302, "NL": 181, "IL": 219, "IE": 173, "FR": 286, "nogeo": 1574635}}