{"ru": {"RU": 31260, "MN": 984, "KG": 251, "KZ": 668, "BY": 2044, "UA": 4395, "US": 205, "UZ": 183, "EE": 139, "DE": 306, "IL": 414, "CZ": 114, "LV": 262, "KR": 150, "nogeo": 979936}, "ar": {"EG": 23560, "LY": 3625, "SA": 115019, "KW": 17951, "BH": 4350, "": 2232, "AE": 9091, "OM": 6718, "QA": 3088, "TR": 1011, "US": 1447, "IQ": 3241, "YE": 974, "JO": 2746, "CA": 192, "FR": 185, "GB": 336, "SY": 308, "LB": 2112, "AU": 185, "TN": 200, "IR": 341, "DE": 228, "JP": 188, "nogeo": 1762971}, "en": {"CA": 46554, "US": 945993, "AU": 20058, "CO": 798, "GB": 155469, "IN": 43038, "TT": 1503, "PH": 36849, "": 2779, "DE": 6526, "SG": 3634, "JP": 3439, "SA": 4427, "BS": 1707, "ID": 9879, "MX": 3284, "BR": 9887, "LC": 424, "MY": 16831, "NG": 49011, "VC": 177, "KW": 2830, "ZA": 40653, "AF": 187, "ES": 6826, "AR": 1445, "PK": 4899, "JM": 3302, "KY": 264, "MV": 644, "NZ": 2362, "EG": 897, "BE": 2186, "PT": 1790, "TH": 2132, "GH": 7873, "BN": 283, "ZW": 1228, "MW": 847, "NO": 328, "IE": 9585, "GD": 192, "CL": 552, "AG": 557, "BB": 1327, "JO": 217, "DK": 591, "DO": 196, "PE": 347, "GU": 252, "HK": 684, "GR": 1243, "TR": 2033, "NL": 3716, "BM": 259, "KE": 7702, "BW": 1342, "LK": 721, "NA": 1451, "CN": 1076, "IT": 2194, "UG": 2405, "KR": 1220, "IS": 179, "SN": 289, "SK": 179, "AE": 4548, "PA": 296, "FR": 3647, "BD": 509, "ZM": 1193, "GT": 187, "CH": 698, "TZ": 834, "UA": 368, "CM": 502, "PL": 398, "BH": 579, "IL": 776, "RW": 481, "SE": 1418, "QA": 845, "LB": 440, "NP": 499, "VN": 281, "LU": 198, "FI": 566, "HN": 189, "MT": 306, "HT": 179, "MZ": 171, "CI": 190, "HR": 459, "SO": 259, "RU": 376, "OM": 460, "RO": 214, "VG": 388, "BG": 240, "TW": 203, "CZ": 309, "CY": 417, "HU": 393, "LY": 224, "SZ": 396, "GE": 176, "AT": 401, "TC": 174, "ET": 190, "LS": 345, "MU": 289, "RS": 184, "IQ": 306, "GI": 214, "XK": 243, "VI": 173, "nogeo": 1652416}, "es": {"CO": 37611, "MX": 73843, "AR": 103838, "PA": 5540, "CR": 2998, "UY": 10530, "ES": 68791, "VE": 7473, "CL": 27074, "PE": 8290, "US": 25857, "PY": 6932, "EC": 8507, "BR": 14538, "DO": 4586, "CA": 1056, "BO": 762, "HN": 2615, "SV": 3272, "GT": 3364, "NI": 1596, "ZA": 181, "": 435, "CU": 226, "PH": 248, "PT": 464, "IL": 220, "DE": 192, "IT": 221, "FR": 335, "nogeo": 1703587}}