{"ru": {}, "ar": {}, "en": {"TT": 1476, "US": 869216, "CA": 36984, "NZ": 2568, "MY": 18322, "AR": 1546, "AU": 19385, "JM": 4357, "GB": 138760, "TH": 2367, "JP": 3081, "MX": 5881, "TW": 386, "PH": 46379, "SA": 4083, "IN": 41638, "IE": 9224, "SG": 3504, "BH": 607, "BS": 2133, "ID": 11950, "ES": 4511, "LC": 573, "PK": 4867, "BR": 10444, "KE": 7658, "LK": 748, "FR": 2834, "NG": 53298, "KY": 252, "BW": 1724, "PA": 518, "DE": 5168, "KN": 397, "GH": 12120, "DK": 569, "BN": 211, "CN": 802, "KR": 1357, "AG": 403, "NO": 229, "UG": 2948, "TC": 195, "BB": 1025, "EG": 1205, "CY": 351, "BM": 173, "MM": 165, "ZA": 45239, "KW": 3069, "NP": 452, "BD": 537, "AE": 4888, "HU": 341, "NL": 3306, "GM": 205, "CO": 703, "HN": 244, "SN": 320, "RU": 645, "PE": 367, "BE": 880, "CL": 556, "PT": 1122, "ZW": 1105, "BG": 178, "LB": 645, "MV": 346, "ZM": 1535, "NA": 1617, "OM": 471, "IR": 167, "QA": 652, "MZ": 234, "TZ": 1146, "PL": 428, "CI": 274, "MW": 1147, "MU": 201, "TR": 1542, "ET": 210, "RW": 412, "SE": 1260, "SZ": 392, "GT": 216, "CM": 376, "GU": 180, "IL": 750, "JO": 212, "KH": 170, "VN": 246, "IT": 1290, "AT": 355, "": 1190, "FI": 506, "LS": 401, "IQ": 425, "UA": 381, "DO": 340, "EC": 165, "SL": 264, "CH": 236, "AW": 268, "MT": 178, "CZ": 290, "GR": 308, "HT": 215, "NI": 165, "LY": 277, "HR": 297, "IM": 181, "VC": 201, "VG": 396, "nogeo": 1618194}, "es": {"CO": 38440, "US": 24601, "MX": 68871, "AR": 100975, "ES": 63856, "CL": 31563, "NI": 1745, "DO": 4083, "PA": 6095, "BR": 14151, "BO": 1225, "PY": 7437, "PE": 7436, "HN": 2208, "EC": 8174, "UY": 12912, "VE": 7477, "CR": 3008, "SV": 1532, "DE": 184, "GT": 3609, "CA": 1014, "CU": 386, "ID": 365, "IT": 224, "PT": 458, "FR": 342, "PH": 182, "NG": 188, "nogeo": 1699757}}