{"ru": {"BY": 1723, "RU": 32662, "UA": 4781, "MN": 1034, "US": 217, "DE": 272, "EE": 111, "KZ": 708, "IL": 463, "KG": 300, "CA": 98, "TR": 105, "UZ": 175, "LV": 199, "BG": 225, "GE": 180, "JP": 106, "KR": 97, "HU": 103, "FR": 101, "IT": 284, "nogeo": 914056}, "ar": {"IQ": 3461, "AE": 10824, "SA": 122306, "": 2708, "KW": 16883, "QA": 3186, "EG": 28272, "BH": 4947, "LY": 3855, "US": 1500, "CA": 220, "OM": 6679, "TR": 724, "LB": 2198, "TN": 763, "JO": 3042, "GB": 650, "AU": 448, "YE": 1472, "IT": 268, "SY": 388, "IR": 322, "MA": 223, "PK": 188, "GR": 217, "DE": 236, "DZ": 185, "nogeo": 1735214}, "en": {"US": 967533, "CA": 46254, "MY": 18999, "AU": 22582, "ZA": 39437, "ID": 11419, "NZ": 3487, "BR": 9238, "GB": 187409, "": 4697, "JM": 3110, "NG": 50471, "JP": 3911, "PH": 44763, "IN": 43005, "SA": 4446, "CR": 191, "MV": 618, "KR": 1226, "HK": 367, "TT": 1574, "DK": 678, "BB": 818, "AE": 4911, "TW": 357, "TH": 2588, "IE": 11742, "BE": 1804, "NL": 3786, "MX": 4021, "FR": 4157, "VN": 263, "IL": 630, "CL": 513, "PK": 5594, "BS": 1465, "ES": 6451, "GH": 7865, "AG": 377, "CO": 758, "RU": 419, "SG": 4152, "DE": 6836, "LK": 687, "KY": 173, "RW": 430, "QA": 720, "PT": 2065, "PL": 359, "LS": 203, "ZM": 1170, "SN": 357, "BW": 1170, "AR": 1316, "CN": 743, "BG": 266, "KE": 6510, "IT": 2530, "LB": 578, "PE": 372, "SE": 1371, "UG": 2361, "CH": 994, "TZ": 666, "KW": 2924, "ZW": 863, "PA": 335, "BD": 386, "RO": 213, "HT": 167, "NA": 1590, "NP": 543, "ET": 238, "EG": 925, "TR": 2126, "BN": 274, "CZ": 506, "MW": 493, "GU": 181, "GR": 1166, "BM": 275, "SZ": 216, "MU": 274, "BH": 866, "HR": 459, "MM": 226, "UY": 165, "UA": 354, "FI": 581, "TC": 178, "VC": 247, "NO": 297, "MT": 383, "OM": 644, "IQ": 292, "AT": 346, "CM": 529, "HU": 413, "SO": 238, "CY": 656, "GD": 206, "XK": 168, "LC": 407, "IM": 217, "JO": 213, "VG": 319, "KN": 169, "GM": 222, "nogeo": 1623633}, "es": {"NI": 1899, "PE": 8805, "CO": 35672, "MX": 73425, "AR": 91024, "ES": 73224, "CL": 25019, "UY": 10278, "US": 23838, "GT": 3301, "DO": 4067, "PA": 5186, "BR": 14388, "VE": 7381, "HN": 2049, "EC": 7451, "PY": 5889, "": 672, "CA": 1051, "CR": 3328, "IT": 482, "BO": 654, "SV": 3240, "PT": 547, "CU": 235, "JP": 260, "PH": 388, "ID": 177, "DE": 387, "NG": 207, "FR": 335, "AT": 176, "IL": 223, "nogeo": 1694302}}