{"ru": {"RU": 25930, "JP": 260, "US": 161, "UA": 3837, "MN": 1721, "KG": 385, "CN": 169, "IL": 672, "BY": 2034, "KZ": 766, "PL": 225, "UZ": 372, "KR": 182, "DE": 187, "CZ": 169, "nogeo": 1310244}, "ar": {"QA": 2737, "SA": 74853, "KW": 15438, "EG": 25004, "IQ": 4584, "LY": 5084, "YE": 757, "OM": 7673, "AE": 8161, "BH": 4391, "US": 235, "": 2350, "TR": 468, "JO": 1732, "LB": 3336, "IR": 552, "FR": 239, "SY": 474, "TN": 284, "nogeo": 2178922}, "en": {"US": 758806, "MY": 11078, "BS": 1682, "CA": 38131, "IN": 68380, "IE": 10499, "NG": 51049, "AE": 4394, "AU": 17330, "PH": 19619, "ZA": 38971, "MX": 1983, "BB": 1183, "BR": 9510, "JM": 3101, "GB": 158995, "": 1772, "CL": 473, "NZ": 3133, "SE": 1115, "ID": 8111, "FR": 1274, "LC": 635, "AR": 1222, "JP": 1313, "TT": 1584, "DE": 4430, "PT": 1018, "BH": 569, "GH": 9177, "EG": 803, "CH": 480, "PA": 457, "BW": 1909, "ES": 3264, "LK": 812, "GT": 213, "AG": 267, "BD": 647, "KE": 7031, "KW": 1547, "PK": 7181, "VG": 204, "NO": 246, "TH": 933, "UG": 3258, "RW": 468, "ZM": 1353, "OM": 536, "CN": 1022, "SN": 272, "SA": 2611, "NL": 2867, "SG": 2450, "CO": 631, "KR": 903, "NA": 2122, "CY": 547, "TR": 1446, "FI": 357, "UA": 294, "ZW": 1351, "BE": 1155, "MW": 1167, "TZ": 614, "QA": 543, "PE": 254, "MV": 395, "PL": 305, "HK": 628, "CD": 369, "SL": 225, "UY": 173, "GR": 265, "IL": 501, "IQ": 510, "SZ": 474, "HN": 188, "NP": 876, "ET": 199, "BG": 199, "HR": 199, "CM": 232, "LS": 289, "AT": 278, "IT": 923, "DK": 298, "LB": 730, "TW": 199, "RU": 255, "CZ": 242, "MU": 177, "KY": 183, "MM": 164, "MZ": 173, "BM": 267, "GM": 197, "LY": 228, "YE": 215, "nogeo": 1603834}, "es": {"AR": 87179, "MX": 68354, "CL": 29164, "ES": 71479, "DO": 6444, "PY": 6358, "CO": 38560, "US": 20854, "VE": 12924, "UY": 10831, "BR": 12905, "GT": 4291, "PA": 6991, "HN": 2917, "EC": 10164, "CU": 1029, "PE": 7309, "CR": 2688, "CA": 982, "SV": 2144, "NI": 1795, "BO": 765, "ZA": 211, "FR": 267, "PT": 474, "DE": 181, "nogeo": 1792718}}