{"ru": {"RU": 10138, "KG": 242, "UA": 1380, "FR": 62, "BY": 609, "KZ": 261, "US": 305, "MN": 1373, "KR": 68, "EE": 186, "AZ": 75, "GE": 68, "CY": 29, "TR": 86, "JP": 75, "IL": 423, "DE": 262, "FI": 19, "MK": 56, "BG": 69, "AE": 12, "CH": 12, "RS": 37, "PL": 127, "ES": 87, "GH": 6, "UZ": 234, "NL": 22, "AU": 20, "CA": 20, "SE": 36, "NO": 34, "GR": 32, "CN": 3, "LV": 59, "SK": 13, "AM": 5, "HU": 26, "ID": 11, "GB": 54, "IE": 92, "TN": 29, "AR": 4, "AT": 69, "BA": 9, "SI": 8, "CZ": 42, "IT": 37, "MD": 8, "BE": 20, "PT": 14, "RO": 3, "LT": 9, "MX": 4, "HR": 3, "NZ": 4, "nogeo": 8}, "fr": {"US": 2313, "FR": 23332, "CM": 1371, "DE": 293, "CD": 918, "CA": 1816, "GR": 66, "PK": 29, "CH": 387, "KH": 4, "ES": 403, "YT": 41, "IN": 189, "TZ": 164, "GP": 208, "AE": 117, "CF": 59, "BE": 1164, "ZA": 107, "KE": 8, "": 8, "DZ": 123, "KZ": 6, "LU": 39, "AU": 69, "BR": 578, "PT": 77, "GA": 84, "MA": 146, "EG": 27, "GB": 194, "IT": 204, "GN": 435, "KM": 8, "RE": 64, "UG": 13, "ID": 26, "LB": 54, "TR": 69, "BJ": 174, "MX": 86, "TG": 137, "NG": 21, "NE": 59, "TH": 14, "CI": 818, "ET": 5, "ML": 166, "AR": 117, "CO": 44, "BF": 74, "CG": 91, "NL": 70, "SN": 746, "MG": 12, "NC": 30, "BG": 8, "HK": 34, "DO": 47, "PH": 21, "ZM": 6, "RS": 23, "GF": 129, "TW": 8, "MC": 13, "IL": 23, "MR": 17, "CU": 28, "RU": 27, "LK": 4, "TD": 35, "JP": 35, "GH": 36, "MQ": 109, "RW": 12, "IE": 31, "BI": 21, "TN": 68, "RO": 13, "EE": 6, "KR": 10, "SA": 20, "FI": 12, "VN": 4, "CY": 11, "SE": 31, "AT": 11, "CN": 12, "IR": 6, "HT": 88, "SD": 3, "CL": 25, "ME": 3, "IS": 4, "MY": 3, "PE": 12, "XK": 11, "PL": 5, "PM": 3, "UY": 13, "BW": 8, "MF": 4, "LR": 8, "PA": 7, "MU": 5, "MT": 6, "AL": 4, "PF": 30, "SR": 4, "nogeo": 8}, "ar": {"OM": 2477, "SA": 33826, "EG": 12887, "QA": 1114, "LY": 1563, "LB": 1117, "KW": 6906, "IR": 566, "AE": 3623, "US": 822, "GB": 823, "IQ": 2990, "BH": 1159, "TR": 968, "": 750, "YE": 620, "JO": 1326, "IT": 93, "UA": 20, "SD": 16, "SY": 277, "CA": 154, "NL": 65, "ID": 28, "DZ": 765, "AU": 71, "MA": 302, "PK": 187, "CH": 111, "IL": 88, "SO": 16, "IN": 22, "ES": 115, "FR": 373, "CN": 9, "AF": 12, "PL": 19, "TN": 271, "DE": 364, "BR": 35, "BA": 21, "SE": 109, "AT": 40, "TH": 15, "DK": 61, "BE": 20, "TD": 7, "IE": 25, "NO": 12, "KE": 5, "AR": 5, "LR": 7, "GR": 19, "HU": 18, "ZA": 19, "CY": 11, "TZ": 4, "AM": 14, "GE": 16, "MY": 16, "BJ": 5, "RU": 26, "BD": 12, "UG": 10, "MR": 10, "PT": 34, "CI": 10, "SN": 6, "SK": 5, "PY": 4, "UZ": 4}, "pt": {"BR": 245020, "AR": 786, "TZ": 89, "CU": 37, "MZ": 283, "MX": 599, "US": 2035, "VE": 33, "DE": 144, "PT": 4576, "ES": 1126, "CA": 276, "ID": 53, "CO": 274, "CR": 20, "GT": 26, "AU": 73, "ZA": 64, "CL": 193, "IN": 101, "IT": 324, "PE": 66, "NI": 20, "FR": 247, "BE": 46, "UY": 107, "NL": 104, "SE": 10, "PH": 23, "PA": 47, "IE": 204, "GB": 284, "EC": 69, "JP": 119, "PK": 26, "PY": 289, "AO": 114, "HN": 25, "IL": 15, "LU": 21, "TR": 45, "HU": 41, "BG": 10, "RU": 10, "HR": 10, "FI": 25, "AE": 16, "LT": 20, "KR": 30, "CV": 12, "RS": 22, "CD": 11, "RO": 12, "EG": 11, "BW": 12, "CH": 15, "SK": 11, "UA": 10, "CN": 31, "BO": 23, "CZ": 14, "DO": 40, "PL": 35, "nogeo": 42}, "en": {"US": 490990, "IN": 41430, "PK": 5648, "GB": 96886, "CA": 27411, "MY": 4082, "PH": 9040, "BE": 736, "ZA": 24127, "AU": 13825, "NZ": 2300, "NG": 8406, "AE": 2483, "SA": 2273, "JM": 1853, "TH": 1120, "ID": 6344, "DE": 3614, "JP": 812, "MX": 1869, "KE": 5643, "UG": 2809, "MV": 195, "NL": 2426, "NP": 355, "IL": 511, "IE": 6972, "BR": 4590, "BW": 1437, "GR": 796, "AT": 237, "GH": 4875, "KW": 546, "RU": 177, "HR": 284, "DK": 334, "TW": 167, "ZW": 855, "BS": 638, "LK": 1618, "SE": 1139, "LB": 250, "MW": 801, "MM": 318, "ES": 3601, "TZ": 669, "SG": 944, "TR": 704, "BH": 347, "": 646, "ZM": 1017, "IR": 242, "CY": 432, "CM": 163, "BD": 917, "IT": 1244, "CH": 409, "OM": 159, "RW": 364, "NO": 197, "SK": 116, "SZ": 140, "NA": 887, "ET": 343, "PL": 234, "PT": 667, "FR": 1025, "KR": 380, "CN": 289, "AR": 948, "UA": 241, "EG": 560, "IS": 259, "RO": 131, "QA": 285, "CZ": 251, "LS": 125, "TT": 793, "MT": 137, "BG": 167, "HU": 161, "VC": 156, "PA": 229, "GT": 133, "AG": 304, "SN": 261, "KH": 568, "BB": 537, "FI": 256, "IQ": 242, "BM": 150, "CO": 586, "CL": 289, "PE": 186, "RS": 153, "CU": 136, "HK": 307, "UY": 123, "LC": 166, "nogeo": 1153969}, "es": {"IT": 542, "ES": 47537, "AR": 49557, "MX": 44583, "PE": 5433, "PA": 3057, "VE": 9068, "CO": 26244, "BO": 824, "PY": 4293, "US": 16916, "UY": 8088, "CL": 17758, "NL": 237, "GT": 2281, "CU": 1455, "HN": 1393, "EC": 6794, "NI": 1200, "FR": 198, "AU": 120, "BR": 6658, "DO": 4249, "CR": 1929, "DE": 539, "TR": 82, "PT": 351, "CA": 482, "SV": 1484, "BE": 97, "ZA": 86, "IL": 252, "IE": 73, "VN": 103, "JP": 68, "ID": 60, "nogeo": 464988}}