{"ru": {"UZ": 206, "RU": 9973, "MN": 1127, "PL": 140, "BY": 610, "KZ": 630, "IL": 124, "KG": 355, "EE": 38, "UA": 1349, "LV": 122, "US": 212, "BG": 143, "HR": 20, "GE": 59, "DE": 221, "LT": 17, "CY": 50, "TR": 105, "DK": 6, "MK": 72, "NZ": 15, "AZ": 72, "AU": 30, "BE": 39, "CA": 43, "SE": 31, "NL": 27, "ME": 15, "FI": 24, "RS": 57, "FR": 89, "GB": 21, "CZ": 88, "KR": 24, "ES": 32, "JP": 44, "HU": 9, "CH": 4, "AR": 8, "AM": 21, "MD": 8, "GR": 31, "AT": 8, "CN": 8, "SK": 30, "IE": 34, "ID": 8, "AE": 6, "MX": 16, "PT": 10, "BR": 4, "nogeo": 9}, "fr": {"SN": 1210, "FR": 22962, "CD": 1515, "CA": 1433, "CM": 1302, "MA": 1087, "MQ": 276, "XK": 118, "US": 1888, "GR": 114, "NC": 25, "BJ": 265, "GT": 15, "DE": 246, "AR": 102, "BR": 886, "GP": 576, "CH": 369, "CI": 779, "BE": 1010, "LB": 52, "IN": 113, "RE": 237, "TZ": 143, "ZA": 193, "TH": 16, "EG": 194, "ES": 924, "CG": 68, "RS": 73, "NP": 8, "PH": 58, "AM": 60, "ML": 162, "SG": 4, "MY": 35, "BW": 12, "DJ": 16, "MW": 8, "KE": 22, "PT": 395, "TN": 243, "GH": 33, "NL": 45, "PK": 19, "MC": 114, "CL": 18, "AE": 193, "IT": 258, "BA": 31, "VN": 10, "TR": 990, "ID": 49, "NZ": 9, "JP": 86, "BF": 66, "CO": 41, "RW": 4, "GB": 204, "YT": 52, "UY": 17, "MX": 218, "DO": 29, "CF": 29, "ET": 7, "GN": 365, "LU": 19, "AL": 99, "AD": 9, "IE": 21, "GF": 106, "RO": 38, "RU": 19, "JM": 18, "": 3, "KM": 24, "HR": 51, "GA": 96, "IL": 34, "PL": 20, "NG": 23, "LT": 5, "BI": 6, "AU": 40, "QA": 11, "BG": 9, "LY": 13, "MG": 8, "SI": 12, "NE": 243, "DZ": 242, "FI": 17, "ZM": 6, "PE": 33, "TG": 94, "TD": 77, "SA": 6, "CN": 9, "HK": 16, "NO": 9, "MK": 16, "MT": 90, "EE": 9, "CY": 47, "AF": 3, "SE": 76, "CU": 12, "CV": 37, "AT": 8, "CZ": 9, "HT": 84, "MR": 15, "BL": 14, "ME": 9, "IS": 7, "PY": 7, "CR": 10, "HN": 9, "PF": 7, "MU": 4, "nogeo": 6}, "ar": {"KW": 5723, "SA": 33504, "EG": 14402, "": 813, "IL": 52, "DE": 320, "IQ": 2216, "LB": 1638, "OM": 3462, "JO": 1142, "PK": 170, "QA": 977, "DZ": 1024, "MA": 413, "LY": 1957, "XK": 7, "IR": 539, "TR": 1481, "BH": 1657, "US": 970, "AZ": 30, "AE": 3431, "FR": 190, "YE": 1507, "AU": 96, "TN": 316, "AT": 40, "CA": 283, "BA": 70, "ES": 223, "JP": 17, "SY": 435, "KG": 12, "GB": 514, "HU": 28, "ID": 33, "IN": 23, "RU": 43, "GE": 278, "IT": 65, "GR": 36, "PL": 55, "KE": 22, "TZ": 13, "CN": 5, "UA": 61, "SD": 16, "SN": 36, "ME": 4, "BE": 55, "CD": 21, "BR": 29, "ZA": 36, "MY": 4, "PT": 13, "CY": 13, "CH": 118, "NL": 128, "MV": 23, "MR": 25, "MZ": 3, "KM": 3, "AF": 18, "SO": 6, "HR": 8, "SE": 40, "TH": 15, "AR": 5, "IE": 47, "BD": 14, "DK": 3, "nogeo": 6}, "pt": {"BR": 287647, "JP": 207, "US": 2474, "CL": 227, "CO": 414, "ES": 1159, "AR": 905, "MX": 891, "RS": 26, "CA": 200, "AU": 86, "IN": 102, "FR": 283, "TZ": 105, "PY": 220, "DE": 301, "PT": 4338, "TH": 12, "PH": 66, "CR": 30, "CU": 51, "MZ": 360, "ZA": 80, "EC": 86, "GT": 55, "IT": 239, "PE": 77, "LU": 18, "NI": 18, "TR": 83, "HR": 30, "BW": 23, "MT": 12, "NL": 64, "AE": 46, "GB": 183, "UY": 168, "SV": 14, "BO": 53, "HN": 25, "AO": 190, "IL": 11, "CZ": 12, "NG": 17, "PA": 56, "ID": 32, "VE": 44, "IE": 112, "NZ": 15, "FI": 27, "SE": 17, "RU": 27, "SK": 14, "DO": 32, "UG": 12, "CV": 29, "EG": 11, "BE": 13, "CH": 27, "PK": 17, "CN": 26, "PL": 12, "KR": 15, "SR": 16, "nogeo": 48}, "en": {"US": 537291, "PH": 12521, "IN": 37796, "NZ": 2423, "GB": 93816, "ES": 3233, "ZA": 25211, "KE": 5324, "PK": 5717, "NL": 2031, "AU": 16111, "CA": 26889, "FI": 218, "MY": 5438, "GH": 5999, "CR": 225, "JP": 1884, "NG": 10295, "JM": 2623, "AE": 2108, "AG": 211, "BW": 1744, "IE": 6926, "UG": 2472, "MW": 1363, "SE": 821, "LK": 666, "SA": 2082, "PE": 218, "MX": 3167, "ZM": 893, "PL": 275, "DE": 3255, "BG": 120, "ID": 4857, "ZW": 951, "BD": 1108, "AR": 927, "MM": 361, "KR": 393, "SG": 1183, "TZ": 811, "TR": 1081, "BR": 5524, "CH": 126, "MV": 224, "CN": 426, "AT": 238, "NA": 1304, "CZ": 168, "HR": 321, "IL": 505, "LB": 449, "RU": 334, "NP": 466, "UA": 269, "KH": 460, "RW": 230, "EG": 360, "CY": 507, "HK": 358, "TW": 212, "IT": 715, "MT": 235, "GM": 188, "BH": 416, "VN": 1047, "OM": 158, "LS": 229, "FR": 1315, "BE": 545, "ET": 302, "TT": 1231, "IR": 247, "HU": 135, "GR": 787, "DK": 266, "QA": 186, "TH": 704, "HN": 223, "NO": 206, "": 539, "CM": 169, "KW": 624, "PT": 544, "IQ": 200, "SN": 234, "LC": 188, "SZ": 140, "BS": 883, "AL": 125, "BB": 825, "GY": 176, "GT": 180, "CL": 403, "GD": 133, "EC": 340, "CO": 490, "UY": 126, "BM": 160, "PA": 259, "BZ": 152, "KY": 160, "RS": 187, "IS": 213, "VC": 142, "CI": 124, "CU": 150, "nogeo": 1193771}, "es": {"CL": 17102, "ES": 51941, "EC": 7105, "MX": 51346, "VE": 8382, "AR": 55323, "PY": 5946, "CA": 533, "UY": 8047, "CO": 29774, "CR": 2076, "PE": 7029, "GT": 2933, "DO": 4998, "US": 15204, "NI": 1305, "BR": 8683, "AU": 253, "CU": 1826, "PA": 3588, "NL": 160, "HN": 1832, "DE": 579, "AE": 58, "IL": 239, "JP": 362, "MT": 61, "PT": 349, "IT": 322, "DK": 62, "SE": 67, "BO": 650, "BE": 63, "SV": 1426, "PH": 116, "ID": 109, "ZA": 118, "TR": 88, "FR": 114, "nogeo": 490838}}