{"ru": {"RU": 6254, "BY": 510, "UA": 733, "KZ": 280, "KG": 141, "MN": 157, "IL": 239, "nogeo": 1065117}, "ar": {"AE": 4656, "SA": 56821, "EG": 16886, "IQ": 3210, "BH": 2209, "SY": 259, "DE": 200, "LY": 2979, "QA": 1134, "KW": 9256, "JO": 951, "PK": 204, "OM": 4068, "LB": 1597, "": 1237, "TR": 368, "YE": 738, "US": 200, "IR": 376, "TN": 238, "IN": 339, "nogeo": 1899886}, "en": {"US": 433372, "NZ": 1689, "CA": 25381, "AU": 14558, "GB": 103852, "MX": 1829, "IN": 58203, "GH": 6471, "MY": 5779, "BR": 5445, "PA": 261, "JM": 1973, "AR": 1043, "AE": 2845, "SA": 1639, "ID": 5132, "NL": 1754, "PH": 11183, "ZA": 24451, "LC": 267, "QA": 234, "KE": 5321, "MM": 4293, "SG": 1786, "JP": 813, "TZ": 717, "KR": 694, "PK": 6248, "TT": 864, "NG": 26829, "DE": 3523, "TR": 768, "IQ": 206, "EG": 626, "BB": 596, "BS": 805, "BD": 552, "ES": 1908, "TH": 1093, "FR": 787, "RW": 215, "CO": 363, "LK": 862, "UG": 2572, "AG": 232, "BW": 1337, "AT": 548, "IE": 7758, "MW": 782, "IT": 754, "NP": 632, "NA": 844, "SE": 419, "": 622, "HR": 306, "DK": 219, "BE": 465, "LB": 572, "BH": 333, "ZW": 811, "CL": 266, "SN": 198, "HK": 285, "CY": 354, "MV": 313, "KW": 248, "CZ": 227, "IL": 434, "ZM": 519, "PT": 351, "RS": 210, "GR": 221, "NO": 190, "BM": 207, "UA": 201, "nogeo": 1863534}, "es": {"BR": 10251, "VE": 8258, "DO": 3357, "PE": 7850, "AR": 61596, "MX": 44948, "EC": 8808, "US": 14351, "CO": 48036, "CL": 19156, "UY": 8973, "PA": 3628, "ES": 54844, "CA": 562, "PY": 4696, "CU": 992, "SV": 2774, "GT": 3443, "NI": 1180, "CR": 2545, "HN": 1430, "BO": 511, "FR": 231, "DE": 191, "PT": 203, "nogeo": 1709360}}