{"ru": {"US": 276, "RU": 9546, "UA": 1081, "FI": 148, "MN": 1201, "KG": 204, "BY": 369, "UZ": 236, "PL": 60, "EE": 117, "DE": 234, "JP": 93, "AU": 71, "IL": 173, "KZ": 291, "LT": 19, "BG": 57, "CN": 13, "AE": 47, "SK": 7, "MK": 92, "GE": 121, "ID": 5, "SG": 11, "HR": 24, "AR": 5, "EG": 28, "RS": 62, "FR": 74, "HU": 20, "TH": 8, "LV": 59, "BE": 7, "KR": 6, "ES": 31, "NL": 39, "CY": 46, "CZ": 72, "RO": 11, "TR": 50, "GB": 107, "MX": 15, "NO": 25, "SE": 37, "MD": 13, "IE": 119, "AZ": 38, "NZ": 16, "PT": 21, "CA": 52, "CH": 20, "IN": 18, "AT": 10, "ZA": 5, "BR": 6, "AM": 11, "SI": 23, "CR": 25, "TJ": 3, "DK": 5, "JO": 4, "ME": 9, "GH": 8, "IT": 3, "DO": 5, "QA": 4, "nogeo": 8}, "fr": {"FR": 21172, "ES": 313, "GN": 488, "US": 1939, "ID": 85, "CM": 1430, "MG": 42, "CI": 610, "CD": 1313, "CH": 461, "TD": 27, "TR": 51, "FI": 27, "CA": 1617, "NL": 60, "BE": 1069, "NG": 9, "LB": 24, "BR": 600, "GA": 104, "BW": 18, "IN": 149, "NC": 49, "BF": 38, "NE": 50, "UG": 12, "CG": 251, "RE": 85, "TZ": 150, "AE": 132, "LU": 47, "BJ": 141, "SA": 15, "DE": 223, "HT": 76, "MX": 93, "AU": 56, "TH": 14, "TN": 41, "DJ": 26, "ZA": 132, "SN": 772, "GH": 33, "CO": 49, "BI": 25, "EG": 55, "IL": 82, "RW": 13, "MA": 145, "KR": 69, "CF": 52, "NP": 3, "CU": 17, "AR": 108, "ML": 134, "XK": 4, "GB": 222, "IT": 197, "CR": 15, "HU": 21, "KE": 24, "TG": 102, "KH": 5, "VN": 14, "NZ": 12, "PH": 20, "DZ": 150, "GR": 38, "PK": 17, "MU": 29, "QA": 3, "SE": 18, "CN": 8, "RS": 52, "JP": 13, "MC": 10, "SG": 3, "GP": 228, "MQ": 171, "RU": 13, "ZM": 3, "CL": 99, "AT": 9, "MN": 3, "YT": 15, "PT": 33, "IE": 18, "PM": 4, "SI": 6, "MT": 21, "PL": 3, "GF": 88, "GQ": 5, "CY": 5, "CZ": 9, "PF": 17, "UY": 18, "PY": 5, "HK": 6, "DK": 8, "BG": 5, "KM": 9, "DO": 12, "MR": 11, "UA": 6, "GM": 9, "EC": 6, "SV": 5, "MF": 3, "NO": 4, "nogeo": 11}, "ar": {"KW": 6511, "EG": 13202, "BH": 1692, "AE": 3576, "SA": 32882, "JO": 1484, "TN": 313, "QA": 939, "FR": 252, "SY": 394, "OM": 2329, "US": 705, "LB": 1292, "IQ": 1882, "YE": 1060, "IR": 624, "DE": 248, "MA": 371, "TR": 775, "LY": 2397, "GB": 923, "SD": 25, "DZ": 1036, "PK": 225, "BJ": 21, "MU": 4, "TH": 11, "IT": 52, "BA": 6, "SE": 39, "BR": 15, "AT": 53, "DK": 6, "ES": 77, "NO": 22, "AM": 28, "CA": 149, "RU": 12, "TZ": 9, "GE": 55, "NL": 134, "CH": 29, "": 32, "MR": 30, "ZA": 50, "ID": 63, "IL": 64, "ET": 8, "UA": 67, "AF": 19, "AU": 77, "PL": 59, "BE": 26, "TD": 5, "MY": 5, "NZ": 3, "IE": 14, "SO": 32, "SK": 8, "KE": 6, "JP": 8, "LT": 5, "FI": 4, "CY": 9, "PT": 5, "VN": 5, "IN": 13, "HU": 7, "KZ": 4, "GR": 30, "NP": 13, "CI": 30, "EC": 9, "RO": 7}, "pt": {"BR": 226570, "ES": 1024, "PE": 43, "PT": 4385, "ZA": 81, "MZ": 366, "MX": 527, "TZ": 107, "IT": 244, "US": 1761, "IE": 218, "IN": 57, "AR": 942, "VE": 112, "JP": 62, "CO": 231, "GH": 30, "ID": 43, "UY": 151, "PH": 33, "AO": 159, "GT": 44, "CN": 9, "CA": 349, "FR": 269, "BW": 29, "EC": 64, "PY": 164, "RS": 39, "GB": 387, "AT": 10, "AE": 74, "BE": 102, "TR": 51, "LU": 10, "NO": 13, "CH": 42, "NL": 60, "IL": 13, "GR": 11, "PA": 47, "FI": 23, "DE": 296, "RU": 10, "BO": 32, "NG": 16, "HN": 20, "PK": 27, "AU": 12, "UA": 11, "CL": 305, "HU": 25, "CU": 31, "KR": 13, "SK": 9, "XK": 13, "CV": 10, "DO": 12, "SE": 14, "NI": 16, "SN": 9, "SV": 19, "IR": 10, "EE": 12, "HR": 12, "nogeo": 28}, "en": {"US": 470536, "ZA": 23655, "PH": 10160, "IN": 35451, "LK": 596, "ZM": 845, "GB": 90694, "AU": 12891, "KE": 7241, "MY": 4646, "IE": 7040, "MX": 1930, "AE": 3199, "ID": 6415, "PK": 5559, "UG": 2990, "LS": 146, "CA": 26601, "CZ": 228, "GH": 6562, "EG": 624, "NZ": 2642, "CH": 340, "NG": 7377, "BW": 1333, "MW": 969, "BD": 1447, "TH": 1296, "TZ": 784, "BH": 315, "SG": 1165, "PE": 190, "SA": 2386, "CY": 399, "NL": 2499, "ZW": 1080, "QA": 320, "PT": 626, "DE": 3881, "NA": 972, "BS": 690, "JP": 748, "SZ": 155, "FI": 198, "CU": 170, "FR": 1194, "ES": 3145, "BR": 4958, "CO": 485, "SE": 717, "IR": 293, "KW": 685, "NP": 386, "IT": 926, "GM": 133, "MM": 258, "VN": 305, "MV": 277, "HU": 244, "JM": 1347, "TR": 1129, "SN": 154, "MT": 219, "RU": 323, "RW": 294, "UA": 470, "CM": 149, "NO": 174, "LB": 276, "OM": 144, "TT": 694, "BE": 900, "GR": 293, "ET": 390, "GT": 150, "BB": 514, "HR": 201, "AR": 848, "CN": 282, "KR": 320, "KH": 123, "IS": 220, "RS": 169, "PL": 212, "AT": 272, "TW": 152, "AG": 216, "IL": 352, "PA": 222, "BM": 159, "BA": 252, "HN": 176, "IQ": 147, "CR": 119, "DK": 348, "CL": 394, "UY": 141, "LC": 119, "VE": 261, "HK": 208, "nogeo": 1178644}, "es": {"EC": 7647, "ES": 44902, "AR": 55772, "CO": 23236, "PA": 3623, "MX": 38947, "US": 13409, "PY": 5158, "TR": 69, "VE": 8031, "GT": 2519, "CL": 28905, "BR": 6554, "DO": 4020, "PE": 5193, "UY": 7905, "SV": 1587, "DE": 432, "HN": 1371, "CR": 2168, "IL": 282, "AE": 87, "NI": 1106, "NL": 361, "AT": 64, "IT": 401, "CA": 687, "CU": 1673, "FR": 220, "GH": 52, "JP": 65, "AU": 134, "DK": 69, "SE": 162, "PT": 303, "GB": 94, "BO": 713, "BE": 182, "CZ": 60, "IE": 78, "PL": 67, "ZA": 103, "HU": 69, "ID": 210, "KE": 64, "IN": 47, "TZ": 64, "nogeo": 456943}}