{"ru": {"RU": 9196, "CN": 23, "MN": 738, "AR": 4, "DE": 271, "UA": 1299, "BY": 251, "PL": 109, "KG": 228, "ES": 110, "BR": 4, "FI": 140, "SK": 56, "GE": 105, "KZ": 280, "AU": 31, "GR": 18, "NZ": 11, "UZ": 194, "US": 212, "SI": 8, "LV": 132, "IL": 128, "MK": 44, "CA": 41, "ID": 19, "BG": 100, "JP": 65, "SE": 78, "GB": 54, "CZ": 62, "AE": 6, "HU": 40, "LK": 49, "FR": 91, "BE": 88, "EE": 12, "TR": 50, "AT": 7, "MD": 4, "PT": 16, "NL": 4, "AZ": 5, "LT": 8, "IT": 3, "CY": 18, "KR": 4, "SC": 12, "AM": 9, "DO": 12, "TH": 4, "CH": 4, "SA": 3, "MX": 22, "RS": 6, "DK": 10, "nogeo": 7}, "fr": {"DE": 165, "FR": 18534, "CD": 1380, "US": 1338, "AE": 154, "RE": 151, "BR": 596, "BE": 730, "GN": 460, "IN": 181, "CM": 1988, "ID": 82, "SA": 32, "MA": 388, "CI": 846, "NE": 64, "SN": 840, "CH": 351, "CA": 1680, "BI": 40, "ES": 377, "BJ": 462, "LB": 37, "OM": 7, "TH": 38, "PA": 13, "AU": 95, "DZ": 134, "TG": 122, "SG": 6, "CO": 53, "IL": 38, "NG": 44, "ML": 255, "IT": 158, "PH": 47, "RW": 34, "FI": 20, "GB": 170, "KR": 6, "CG": 60, "TN": 90, "ET": 14, "RU": 154, "PK": 38, "TZ": 150, "PF": 34, "GA": 80, "EG": 85, "MG": 43, "GP": 155, "ZA": 85, "LU": 61, "MC": 26, "CN": 35, "AR": 110, "HT": 96, "NC": 28, "IE": 40, "CF": 51, "GH": 26, "MT": 8, "JP": 23, "KE": 14, "MY": 27, "CL": 24, "MX": 87, "NL": 54, "NO": 10, "MQ": 112, "TR": 55, "UG": 26, "TD": 57, "ZM": 4, "PG": 3, "DK": 3, "YT": 17, "GF": 121, "PT": 46, "BD": 152, "IR": 13, "DO": 21, "DJ": 11, "KW": 3, "SE": 21, "LT": 27, "BF": 173, "UY": 23, "KM": 4, "EC": 8, "NZ": 3, "RS": 14, "CY": 17, "LR": 7, "SV": 24, "MR": 6, "PE": 24, "CR": 14, "BY": 6, "GQ": 6, "BH": 14, "AT": 7, "MF": 5, "PL": 10, "MU": 11, "HN": 9, "BL": 8, "nogeo": 17}, "ar": {"SA": 35485, "EG": 12047, "KW": 6520, "LY": 1896, "GR": 20, "IQ": 2800, "TR": 1051, "AE": 3459, "JO": 1458, "OM": 2080, "PK": 257, "QA": 812, "SD": 820, "DZ": 745, "LB": 1237, "CY": 13, "CH": 38, "SY": 188, "BH": 1687, "MT": 19, "MA": 513, "ID": 70, "": 55, "AT": 39, "YE": 942, "SN": 18, "TN": 367, "IR": 646, "IL": 48, "IT": 108, "SE": 50, "IN": 42, "BD": 3, "DE": 280, "BE": 103, "CA": 304, "FR": 133, "US": 556, "GB": 580, "ES": 110, "RU": 40, "PH": 8, "HU": 14, "UA": 21, "MY": 20, "LK": 5, "NG": 10, "NL": 63, "AU": 65, "BR": 12, "SO": 15, "TH": 20, "JP": 3, "AO": 13, "FI": 67, "AZ": 6, "MR": 40, "DK": 3, "AM": 13, "GE": 30, "MX": 5, "CM": 32, "CN": 8, "BA": 18, "AF": 21, "CI": 34, "SG": 4, "NZ": 10, "IE": 35, "PL": 8, "GN": 9, "SC": 4, "ET": 7, "TD": 8, "BJ": 6, "NO": 4, "nogeo": 3}, "pt": {"BR": 217824, "MZ": 388, "PA": 43, "PT": 3807, "AR": 828, "US": 1600, "CH": 52, "ZA": 72, "SE": 9, "EC": 56, "MX": 488, "PY": 197, "CU": 28, "ES": 943, "IN": 70, "ID": 33, "CO": 300, "IR": 62, "TZ": 106, "JP": 121, "AO": 190, "IE": 142, "DE": 236, "PH": 26, "NG": 38, "AE": 148, "PE": 87, "CA": 240, "PK": 41, "FR": 246, "UY": 119, "BO": 14, "CD": 11, "SG": 11, "CR": 25, "GT": 47, "GB": 185, "AU": 56, "DK": 13, "RU": 29, "IT": 267, "GH": 18, "NL": 60, "MY": 11, "TR": 58, "FI": 15, "CZ": 21, "HU": 10, "PL": 27, "CL": 228, "KR": 24, "IL": 12, "BW": 16, "TW": 10, "EG": 25, "LU": 41, "DO": 36, "RS": 15, "VE": 38, "AT": 13, "NI": 11, "MV": 11, "BE": 19, "CV": 33, "HN": 32, "RO": 26, "nogeo": 28}, "en": {"AU": 12490, "GB": 79448, "CA": 24034, "US": 321187, "MY": 3877, "PH": 8938, "ZA": 22668, "IN": 39617, "NZ": 2295, "PK": 6063, "MX": 1972, "IL": 480, "GH": 5473, "MW": 894, "UG": 3912, "KE": 6489, "RW": 177, "ID": 6780, "JM": 1108, "SA": 11973, "JP": 762, "NG": 23760, "NA": 738, "CH": 165, "IE": 7018, "AE": 2897, "ZW": 926, "ZM": 830, "SE": 619, "PL": 246, "DE": 3477, "CI": 130, "ES": 3326, "TH": 1272, "TZ": 837, "LS": 176, "CY": 171, "SG": 731, "TR": 2022, "NO": 185, "BR": 4742, "DK": 414, "LK": 537, "QA": 350, "CL": 332, "BW": 1099, "FR": 1174, "": 128, "IQ": 169, "KR": 518, "GM": 242, "NL": 2249, "CN": 653, "LB": 296, "UA": 519, "BE": 743, "SD": 227, "IT": 977, "BD": 1204, "CM": 367, "RU": 378, "AR": 1084, "IR": 552, "AT": 218, "EG": 468, "SL": 202, "BH": 281, "VN": 156, "TW": 272, "NP": 432, "ET": 212, "TT": 536, "FI": 236, "BB": 425, "HU": 164, "PT": 416, "RO": 128, "CO": 621, "SZ": 184, "CD": 137, "HR": 152, "KH": 127, "PA": 213, "GR": 181, "BS": 253, "DO": 120, "SN": 135, "MV": 177, "CZ": 206, "BG": 127, "KW": 322, "CR": 148, "MT": 128, "PE": 172, "UY": 131, "RS": 129, "OM": 152, "IS": 138, "nogeo": 1186925}, "es": {"MX": 39887, "CO": 26510, "ES": 42460, "PA": 2960, "CR": 3719, "AR": 53032, "US": 10465, "GT": 2008, "PY": 5963, "NI": 834, "DE": 494, "HN": 1856, "SV": 1294, "CL": 16763, "BR": 6145, "PE": 7612, "VE": 9787, "SE": 70, "UY": 9563, "EC": 6237, "IL": 165, "IE": 85, "DO": 4371, "FR": 247, "ZA": 120, "CU": 1225, "AE": 162, "AU": 170, "CA": 635, "CN": 60, "NL": 175, "GB": 52, "IT": 734, "BO": 461, "PT": 254, "TR": 100, "NG": 77, "ID": 243, "DK": 50, "TZ": 45, "nogeo": 449322}}