{"zh": {"CN": 7201, "TW": 5213, "HK": 163, "NZ": 128, "AU": 236, "US": 524, "JP": 645, "TH": 145, "FR": 105, "AE": 65, "KR": 58, "CA": 223, "SG": 108, "KH": 17, "MO": 32, "MY": 120, "ES": 17, "UA": 22, "GB": 54, "DE": 65, "NL": 15, "GR": 12, "PH": 15, "MM": 80, "ID": 13, "QA": 14, "LB": 3, "LA": 7, "PK": 5, "IT": 11, "IE": 13, "RU": 3, "PT": 9, "EC": 8, "BR": 7, "AO": 10, "TR": 6, "LK": 14, "MX": 3, "IQ": 5, "PL": 7, "OM": 3, "IN": 4, "MP": 3, "HU": 3}, "ru": {"RU": 4278, "UZ": 282, "JP": 71, "LV": 173, "UA": 654, "MN": 1173, "BG": 109, "GE": 470, "BY": 345, "US": 373, "IL": 406, "KZ": 504, "CY": 28, "TR": 261, "SK": 69, "NL": 90, "KR": 45, "MK": 54, "AE": 19, "AM": 90, "IT": 88, "CA": 134, "EE": 78, "TH": 63, "DE": 308, "CH": 29, "KG": 349, "CN": 49, "IN": 64, "RS": 46, "FR": 50, "ID": 24, "MD": 17, "AU": 21, "AZ": 125, "AT": 21, "GB": 118, "ES": 40, "LT": 60, "VN": 9, "CZ": 41, "PL": 183, "SE": 48, "SA": 15, "AQ": 6, "IE": 8, "PT": 72, "ME": 43, "NO": 40, "BA": 12, "AR": 25, "JO": 21, "SI": 16, "IQ": 10, "RO": 27, "TN": 4, "MY": 11, "MX": 4, "DO": 34, "BE": 3, "HK": 4, "LU": 9, "nogeo": 11}, "fr": {"DE": 312, "OM": 3, "FR": 24116, "US": 1686, "MX": 301, "CM": 2115, "ZA": 128, "CD": 1532, "ES": 489, "BE": 1445, "BR": 950, "CA": 2640, "AE": 85, "TZ": 56, "SG": 8, "TG": 238, "SN": 872, "KE": 34, "IN": 207, "AR": 143, "RW": 6, "TN": 84, "PH": 35, "GR": 29, "BJ": 327, "MQ": 183, "CI": 763, "DJ": 23, "MG": 41, "CH": 315, "NG": 71, "BI": 57, "GA": 91, "ID": 51, "AU": 120, "GP": 361, "NL": 50, "TH": 58, "BW": 16, "MC": 33, "VE": 4, "LU": 60, "DZ": 190, "QA": 324, "YT": 43, "NE": 122, "GN": 417, "RU": 11, "IL": 26, "IT": 90, "AD": 6, "TR": 85, "MW": 9, "MA": 233, "VN": 28, "RE": 98, "GB": 202, "PT": 105, "MU": 8, "ET": 15, "MY": 65, "PK": 69, "KR": 42, "JP": 155, "EG": 36, "NC": 16, "SA": 134, "UG": 30, "CG": 75, "PL": 11, "BF": 107, "HU": 18, "PF": 15, "LA": 5, "LB": 23, "ML": 210, "HK": 23, "SE": 71, "MR": 11, "TD": 118, "RO": 9, "KZ": 5, "CZ": 5, "UA": 39, "GH": 32, "KM": 10, "DK": 12, "CY": 11, "CF": 16, "KH": 16, "EE": 3, "HT": 107, "CL": 44, "CO": 80, "BH": 17, "NO": 4, "AO": 22, "LR": 12, "IE": 35, "PE": 14, "AT": 12, "NA": 5, "SR": 3, "UY": 26, "RS": 10, "GF": 41, "GT": 12, "DO": 46, "PA": 13, "LV": 9, "MF": 5, "SK": 7, "BG": 13, "TW": 7, "EC": 15, "HN": 6, "BD": 10, "CR": 6, "AL": 3, "CU": 7, "": 6, "SY": 4, "SX": 3, "nogeo": 4}, "ar": {"KW": 6941, "SA": 50031, "NP": 20, "EG": 14744, "QA": 3685, "AE": 4572, "LY": 1959, "JO": 1355, "NL": 136, "BH": 1501, "AT": 128, "DE": 658, "DZ": 945, "OM": 3247, "IQ": 2698, "TR": 707, "TH": 66, "LB": 1490, "US": 770, "ID": 63, "GB": 801, "SD": 1004, "YE": 1219, "AU": 113, "FR": 233, "IR": 630, "SY": 405, "PK": 279, "MY": 28, "TN": 393, "": 44, "IN": 105, "CA": 259, "ET": 6, "IL": 73, "MA": 661, "TD": 31, "SE": 28, "VN": 71, "NG": 31, "RU": 30, "IT": 125, "CH": 168, "JP": 56, "AR": 44, "AZ": 16, "IE": 21, "PL": 62, "AO": 6, "BE": 76, "ES": 84, "DK": 59, "SO": 16, "AF": 36, "KR": 10, "ML": 5, "GR": 18, "PT": 49, "CY": 12, "EE": 4, "HU": 14, "ZA": 7, "MR": 81, "CN": 14, "DJ": 22, "LK": 4, "KE": 4, "KH": 13, "BR": 43, "NZ": 11, "BT": 7, "MT": 4, "SK": 6, "BD": 5, "PH": 3, "RO": 6}, "pt": {"BR": 294411, "FR": 381, "CZ": 62, "US": 2437, "IN": 141, "MX": 687, "MZ": 385, "PT": 5434, "ES": 1574, "JP": 193, "PH": 28, "CO": 461, "IE": 345, "ZA": 46, "AR": 1366, "BE": 157, "CA": 490, "AT": 15, "AU": 179, "CL": 304, "UY": 184, "DE": 339, "SE": 102, "GB": 668, "CR": 69, "QA": 373, "PK": 39, "NL": 132, "IL": 55, "PE": 111, "CH": 93, "AE": 65, "PA": 114, "SA": 52, "AO": 214, "PY": 241, "IT": 268, "KE": 24, "TZ": 64, "EC": 79, "BW": 21, "DO": 67, "NG": 58, "CV": 35, "ID": 36, "GH": 27, "KR": 24, "FI": 66, "HR": 29, "DK": 17, "VE": 48, "RS": 44, "NI": 16, "NP": 10, "": 9, "BO": 43, "TR": 45, "CU": 24, "HU": 32, "LU": 120, "ST": 11, "BG": 14, "IS": 9, "GP": 23, "GT": 76, "HN": 44, "SR": 19, "MT": 10, "NZ": 9, "AD": 18, "SY": 13, "HK": 12, "nogeo": 23}, "en": {"SA": 1172931, "US": 427898, "CA": 28678, "MY": 6238, "IN": 45456, "PH": 8991, "GB": 95653, "ZA": 19115, "AE": 4332, "AU": 14723, "ES": 3983, "KE": 8510, "ID": 8135, "NP": 666, "UG": 4928, "LK": 732, "TH": 1480, "MX": 2439, "NG": 28929, "BW": 1087, "ZM": 976, "TR": 1777, "TZ": 1005, "GH": 6549, "QA": 2798, "EG": 868, "PK": 7077, "IL": 932, "DE": 5147, "OM": 326, "HR": 223, "JP": 1403, "NA": 850, "IE": 7109, "ZW": 1213, "MW": 1114, "SE": 927, "JM": 1859, "FR": 1638, "NL": 2401, "SG": 1641, "GR": 421, "BE": 1249, "KW": 801, "": 167, "CL": 713, "CY": 367, "BD": 1268, "RW": 274, "CH": 543, "DK": 322, "TW": 201, "NZ": 2289, "CN": 621, "CM": 149, "AL": 149, "PT": 803, "BG": 436, "SZ": 170, "IQ": 172, "MV": 223, "BH": 411, "RO": 193, "BB": 370, "PA": 356, "LR": 210, "IT": 1277, "MT": 195, "CD": 225, "AT": 315, "SN": 165, "LB": 420, "AG": 161, "BR": 5672, "JO": 161, "IS": 292, "GM": 169, "CZ": 247, "KH": 274, "UA": 622, "IR": 205, "TT": 926, "LS": 266, "BS": 531, "VN": 255, "SL": 181, "KY": 140, "KR": 570, "NO": 218, "HU": 274, "RU": 159, "HN": 153, "VC": 137, "AR": 878, "GT": 190, "CO": 705, "ET": 284, "PL": 396, "UY": 144, "FI": 296, "PE": 289, "SY": 165, "CR": 139, "BM": 135, "HK": 296, "RS": 182, "nogeo": 1243984}, "es": {"US": 15841, "ES": 57658, "AR": 53145, "MX": 48359, "CO": 34269, "CL": 17964, "UY": 8574, "DO": 4656, "SV": 1413, "CR": 5335, "BR": 9893, "PE": 6558, "BG": 63, "PA": 4627, "AU": 290, "CU": 1204, "GQ": 84, "HN": 2569, "PY": 4360, "FI": 109, "FR": 372, "VE": 10504, "QA": 1800, "SA": 141, "BE": 100, "IE": 147, "CA": 1239, "NI": 935, "DK": 70, "TZ": 65, "PT": 340, "CH": 89, "IT": 715, "NG": 103, "NL": 333, "IL": 192, "GT": 3729, "EC": 8408, "MT": 49, "DE": 832, "BO": 1125, "CZ": 44, "TR": 114, "GB": 221, "AE": 188, "SE": 82, "JP": 164, "ID": 216, "ZA": 93, "KE": 63, "MY": 61, "IN": 41, "GH": 55, "PH": 47, "PK": 64, "HK": 69, "KR": 50, "nogeo": 393149}, "it": {"IT": 18305, "BR": 1427, "IN": 105, "PH": 99, "MY": 41, "MX": 234, "KE": 23, "QA": 31, "US": 763, "AR": 317, "ZA": 75, "EC": 30, "IE": 20, "NL": 39, "CH": 229, "BW": 16, "ES": 445, "TH": 22, "DK": 15, "JP": 8, "GT": 24, "AU": 21, "BE": 45, "GB": 97, "FR": 182, "TZ": 25, "TN": 5, "EG": 26, "DE": 157, "SE": 34, "NG": 40, "CY": 17, "IL": 4, "ID": 21, "CD": 4, "CL": 83, "UG": 13, "GH": 19, "AE": 34, "MT": 7, "TR": 44, "AT": 12, "SA": 22, "VA": 8, "CO": 85, "IS": 8, "CU": 9, "PT": 26, "HR": 16, "RU": 12, "RS": 16, "UY": 28, "PY": 18, "LS": 4, "DO": 13, "CZ": 5, "VE": 32, "GR": 25, "SG": 6, "SN": 12, "PE": 33, "CA": 53, "EE": 3, "PA": 50, "CR": 33, "PL": 3, "NO": 4, "AZ": 5, "HU": 5, "NI": 7, "FI": 7, "JM": 7, "BD": 4, "nogeo": 11}, "hi": {"IN": 33844, "KE": 56, "PK": 871, "UG": 18, "US": 174, "NP": 302, "KG": 9, "AE": 145, "NG": 63, "SA": 173, "ID": 50, "AU": 30, "MY": 49, "BF": 12, "MV": 33, "ES": 10, "ZA": 83, "QA": 24, "TZ": 44, "BD": 23, "GH": 16, "BH": 7, "BR": 39, "OM": 21, "JP": 69, "CA": 91, "LR": 4, "RW": 7, "BW": 12, "CH": 4, "GB": 23, "KW": 25, "CN": 4, "": 8, "LK": 7, "PL": 3, "XK": 3, "VN": 3, "FR": 11, "IQ": 8, "DK": 5, "TH": 17, "KZ": 3, "SO": 5, "HU": 3, "PT": 4, "RU": 4, "NZ": 4}, "uk": {"PL": 125, "UA": 2514, "IL": 16, "US": 20, "IT": 13, "JP": 19, "BY": 15, "BG": 21, "CA": 28, "AL": 7, "IE": 40, "CZ": 11, "FR": 16, "SE": 21, "TR": 5, "DE": 25, "GE": 9, "GB": 28, "FI": 21, "LT": 13, "ME": 7, "BE": 19, "ES": 18, "AT": 11, "EE": 17, "PT": 12, "KR": 5, "RO": 4, "NO": 3, "NL": 5, "IN": 4, "IS": 3, "CO": 3, "nogeo": 36}, "nl": {"NL": 11159, "CN": 10, "US": 384, "PK": 149, "IN": 125, "BE": 1818, "ZA": 157, "PH": 36, "ID": 64, "MY": 43, "IT": 58, "DE": 163, "TH": 136, "NG": 63, "MT": 33, "ES": 144, "EG": 7, "TR": 60, "TZ": 9, "UA": 8, "RO": 33, "GB": 35, "FR": 24, "JP": 10, "AT": 6, "QA": 41, "KE": 14, "CZ": 17, "GH": 44, "CH": 35, "CW": 7, "PT": 45, "NA": 10, "SA": 22, "CA": 29, "LS": 6, "BR": 83, "EE": 15, "IE": 3, "SR": 4, "PL": 4, "AE": 5, "SE": 10, "PA": 11, "AR": 17, "HU": 3, "SK": 6, "BG": 12, "UY": 3, "MX": 4, "nogeo": 7}, "ko": {"US": 130, "KR": 6454, "JP": 318, "NL": 30, "CA": 11, "CN": 10, "TW": 6, "HK": 3, "ZA": 8, "IN": 9, "BR": 12, "IT": 24, "ID": 14, "FI": 4, "AU": 4, "FR": 4, "TN": 4, "KW": 6, "BS": 7, "SA": 3}, "de": {"DE": 12594, "LU": 53, "AT": 1132, "CH": 705, "SA": 193, "US": 700, "SE": 9, "ZA": 100, "CN": 7, "BR": 223, "ES": 175, "IN": 51, "AE": 21, "UA": 44, "TR": 61, "PH": 22, "NL": 165, "ID": 66, "FR": 80, "EG": 10, "NG": 31, "CA": 37, "JP": 21, "QA": 58, "MT": 3, "GB": 55, "CZ": 37, "BG": 21, "IQ": 4, "MX": 26, "IL": 19, "KR": 9, "GR": 22, "PT": 8, "BE": 66, "IT": 46, "PK": 25, "BH": 15, "AR": 48, "LY": 5, "GH": 16, "PL": 22, "TW": 4, "LI": 7, "AU": 11, "TH": 5, "MY": 35, "MN": 4, "CL": 14, "IE": 5, "MA": 4, "ZW": 7, "UY": 22, "CO": 20, "HN": 8, "SG": 4, "KE": 7, "IR": 6, "GE": 19, "BD": 5, "RS": 7, "LB": 4, "nogeo": 38}}