{"zh": {"NZ": 27, "CN": 5589, "HK": 196, "TW": 3911, "JP": 554, "AU": 251, "DE": 24, "US": 494, "NO": 17, "ES": 4, "SG": 74, "FR": 117, "CA": 114, "MY": 111, "KR": 31, "TH": 102, "GB": 59, "AE": 28, "UA": 10, "MO": 15, "KH": 8, "QA": 3, "LA": 3, "NL": 55, "GR": 20, "IT": 4, "MM": 51, "VN": 5, "PT": 5, "CH": 10, "PH": 14, "ET": 4, "IR": 4, "PL": 8, "EC": 13, "MX": 4, "EG": 3, "VU": 4}, "ru": {"IL": 299, "RU": 3432, "CN": 190, "MN": 798, "UA": 520, "TR": 110, "CY": 79, "KZ": 348, "AT": 20, "KG": 117, "UZ": 203, "AZ": 33, "GB": 66, "SE": 46, "US": 322, "CA": 245, "AU": 26, "BY": 212, "TH": 46, "EE": 72, "DK": 3, "GE": 306, "BG": 54, "JP": 54, "DE": 508, "RS": 125, "ES": 50, "MD": 34, "LV": 77, "EG": 15, "CZ": 78, "SK": 35, "IT": 68, "PL": 89, "KR": 18, "PT": 57, "FI": 8, "BA": 7, "AE": 20, "MK": 72, "FR": 19, "ID": 36, "RO": 8, "VN": 7, "NL": 38, "SI": 8, "HU": 14, "AM": 95, "ME": 39, "LT": 35, "IE": 29, "NO": 23, "MY": 7, "IN": 7, "NZ": 13, "PH": 10, "BR": 3, "GR": 6, "AL": 5, "PE": 8, "AR": 14, "IS": 6, "nogeo": 10}, "fr": {"FR": 19125, "DE": 226, "ES": 515, "GP": 307, "MX": 73, "CD": 1423, "CA": 1656, "TH": 53, "ML": 160, "SN": 602, "CM": 1528, "US": 1103, "NC": 5, "BI": 43, "RE": 73, "BE": 862, "LU": 33, "KE": 27, "CI": 435, "IT": 83, "CH": 177, "PL": 12, "JP": 80, "QA": 23, "BJ": 138, "AU": 40, "MG": 21, "VN": 14, "TW": 36, "ID": 37, "RO": 7, "UY": 16, "TG": 85, "NO": 10, "IN": 62, "DZ": 123, "PK": 15, "BR": 396, "GB": 160, "KH": 7, "GA": 69, "BF": 69, "TZ": 52, "ZA": 97, "NL": 86, "PT": 63, "MY": 15, "UG": 14, "RW": 19, "AE": 349, "FI": 9, "GF": 54, "KR": 41, "IE": 23, "TN": 86, "YT": 44, "RS": 12, "PF": 13, "GN": 223, "LB": 20, "NG": 27, "NZ": 12, "SE": 16, "PE": 18, "IL": 15, "DJ": 22, "CZ": 5, "KZ": 8, "NE": 90, "CG": 33, "AO": 26, "MU": 11, "MC": 11, "TD": 27, "CO": 57, "TR": 36, "MA": 90, "SA": 28, "AM": 6, "HT": 57, "GE": 4, "HK": 21, "GR": 30, "PH": 19, "MF": 8, "EG": 15, "PA": 4, "AR": 80, "HU": 24, "DK": 19, "CL": 20, "MQ": 102, "SK": 4, "CR": 7, "SG": 6, "CN": 8, "CF": 4, "KM": 23, "EC": 12, "IR": 5, "DO": 4, "BH": 3, "nogeo": 5}, "ar": {"EG": 9291, "BH": 851, "AU": 112, "SA": 23693, "KW": 5155, "IR": 484, "US": 469, "SD": 604, "IQ": 2118, "TD": 9, "LB": 1031, "CA": 171, "OM": 1691, "TN": 297, "JO": 951, "TR": 598, "YE": 788, "AE": 2699, "BE": 47, "DZ": 704, "PK": 215, "QA": 876, "MY": 12, "HR": 23, "LY": 1039, "FR": 133, "DE": 197, "SY": 262, "GB": 500, "CH": 9, "RU": 12, "SE": 48, "MA": 495, "AF": 28, "BD": 3, "IL": 36, "ES": 54, "IT": 148, "NL": 58, "": 42, "NG": 28, "AT": 40, "NO": 72, "ID": 44, "ET": 6, "IN": 25, "SC": 18, "TH": 41, "CZ": 5, "KE": 10, "GH": 14, "NE": 4, "PL": 29, "GR": 25, "BA": 45, "AZ": 11, "CY": 5, "HU": 13, "CN": 7, "BR": 4, "CI": 12, "PA": 15, "DK": 14, "VE": 12, "AR": 28, "NZ": 5}, "pt": {"BR": 192343, "MX": 473, "US": 1538, "AU": 175, "CA": 336, "SA": 19, "AO": 246, "PT": 4161, "TZ": 33, "ZA": 35, "MZ": 233, "CO": 291, "AR": 894, "ES": 911, "NL": 95, "BG": 16, "GB": 515, "EC": 53, "TR": 48, "CH": 46, "DE": 297, "IT": 223, "JP": 96, "DK": 12, "IE": 211, "FR": 163, "IN": 55, "PA": 59, "SG": 9, "PK": 21, "BE": 59, "FI": 31, "CL": 199, "BW": 10, "CI": 14, "DO": 16, "NG": 26, "ST": 11, "IS": 8, "SE": 21, "CN": 27, "AT": 13, "ID": 33, "AE": 22, "RS": 11, "MT": 10, "PY": 151, "UY": 158, "UG": 15, "BO": 24, "GT": 33, "PE": 67, "VE": 42, "HN": 21, "QA": 9, "HU": 11, "CU": 18, "NZ": 34, "HK": 15, "nogeo": 31}, "en": {"IN": 41926, "GH": 5334, "NG": 28566, "US": 335742, "PH": 6919, "CA": 19569, "GB": 72640, "AU": 12161, "ZA": 14307, "PK": 5310, "BW": 970, "IE": 5669, "MW": 949, "SE": 485, "UG": 4645, "AE": 2345, "KH": 148, "KE": 7046, "ID": 4045, "MY": 3589, "LK": 655, "LS": 154, "GM": 236, "NA": 894, "DE": 3146, "ES": 2629, "TH": 1122, "LB": 308, "FR": 1406, "BD": 917, "UA": 487, "IT": 794, "ZW": 824, "BR": 4105, "ZM": 885, "JP": 825, "IL": 520, "NZ": 1756, "MX": 1772, "PE": 213, "TR": 601, "RW": 520, "OM": 198, "QA": 465, "HR": 127, "CZ": 190, "HK": 398, "BE": 755, "SA": 1769, "SG": 803, "NL": 1602, "CH": 302, "BG": 146, "CY": 293, "VN": 220, "ET": 252, "TZ": 619, "BH": 406, "": 156, "IR": 244, "PL": 328, "SZ": 157, "IQ": 138, "GR": 203, "SL": 204, "NP": 408, "HU": 137, "KR": 410, "TW": 191, "AT": 238, "JM": 1246, "EG": 709, "CN": 279, "CO": 611, "NO": 161, "TT": 577, "AR": 720, "UY": 139, "BS": 355, "PT": 506, "CL": 292, "GE": 226, "CI": 137, "DK": 248, "FI": 180, "BB": 332, "PA": 176, "GT": 329, "KW": 129, "RS": 199, "nogeo": 1185566}, "es": {"CO": 26689, "US": 11131, "MX": 41094, "AR": 47603, "CL": 13809, "EC": 6644, "ES": 38079, "IL": 213, "UY": 7146, "VE": 9278, "CA": 873, "JP": 105, "PE": 4859, "GT": 2327, "DE": 630, "PA": 3041, "PY": 4134, "IT": 341, "BR": 4824, "SV": 1255, "AU": 242, "DO": 3914, "NL": 326, "FR": 302, "CU": 732, "ZA": 63, "BE": 131, "IE": 158, "GB": 42, "BO": 429, "CR": 1568, "NI": 814, "DK": 50, "VN": 74, "PT": 316, "HN": 1287, "ID": 43, "HU": 46, "TR": 74, "AL": 67, "AE": 64, "NG": 52, "nogeo": 414710}, "it": {"IT": 13052, "DE": 156, "ES": 209, "BR": 786, "US": 459, "FR": 128, "TR": 35, "IN": 109, "PE": 33, "NG": 15, "ZA": 73, "GB": 135, "CH": 120, "CL": 53, "MX": 184, "UG": 10, "KR": 7, "CO": 96, "SG": 5, "AU": 8, "CZ": 3, "DK": 6, "TH": 22, "EG": 5, "NL": 39, "PL": 32, "AE": 10, "MC": 11, "CR": 13, "PH": 22, "BE": 36, "MY": 9, "TZ": 15, "MT": 18, "AR": 234, "SI": 5, "PT": 36, "VA": 9, "CA": 41, "IL": 5, "HN": 6, "PK": 4, "KE": 15, "DO": 28, "VE": 45, "BW": 8, "UY": 32, "EC": 31, "PA": 15, "GT": 10, "IE": 3, "SE": 4, "PY": 15, "JP": 10, "CU": 13, "AT": 7, "SK": 5, "CY": 7, "NI": 7, "SM": 4, "HK": 12, "nogeo": 5}, "hi": {"IN": 43411, "TZ": 43, "PK": 602, "NG": 80, "NP": 242, "AE": 178, "TH": 14, "US": 81, "FR": 18, "AU": 27, "SA": 97, "UG": 39, "CA": 43, "ZA": 50, "ID": 19, "MY": 14, "IR": 6, "QA": 23, "IT": 4, "": 3, "CN": 6, "GH": 8, "CH": 3, "BR": 24, "OM": 12, "MV": 10, "NZ": 4, "NA": 14, "GB": 40, "SO": 8, "KE": 14, "BW": 5, "MW": 14, "VN": 5, "ET": 3, "TR": 5, "BD": 4, "DE": 9, "MX": 9, "BH": 3}, "uk": {"RU": 69, "RS": 29, "UA": 1867, "US": 25, "IL": 36, "PL": 75, "CA": 13, "FI": 12, "IE": 29, "GE": 10, "NL": 5, "LT": 12, "BY": 11, "DE": 78, "UZ": 18, "BE": 10, "BG": 7, "PT": 7, "IT": 15, "NO": 6, "AL": 12, "CZ": 4, "nogeo": 35}, "nl": {"NL": 8498, "ZA": 95, "JP": 40, "BE": 1427, "US": 214, "DE": 145, "ES": 129, "TZ": 11, "PK": 114, "NG": 56, "GR": 17, "FR": 54, "IN": 59, "SA": 23, "AU": 18, "TR": 22, "MY": 22, "ID": 60, "IT": 132, "CA": 27, "AT": 46, "SE": 9, "UG": 13, "PT": 63, "CH": 19, "SK": 11, "AR": 7, "GB": 22, "NO": 21, "BG": 21, "RW": 4, "BD": 3, "BR": 42, "IL": 8, "SN": 5, "TH": 5, "DK": 9, "IE": 4, "CO": 5, "HU": 6, "SR": 6, "nogeo": 11}, "ko": {"KR": 4993, "JP": 114, "AU": 7, "TH": 42, "FR": 20, "CA": 39, "US": 129, "AT": 16, "SG": 11, "IN": 14, "TW": 12, "MY": 9, "VN": 8, "HK": 4, "ZA": 9, "ID": 9, "BR": 8, "PE": 3, "CO": 16}, "de": {"DE": 9586, "IN": 142, "ZA": 43, "AT": 879, "CZ": 17, "CH": 592, "DK": 19, "UA": 42, "US": 360, "IT": 72, "BE": 50, "GB": 34, "TN": 13, "ID": 31, "FR": 38, "NG": 32, "GH": 14, "TR": 17, "FI": 90, "NL": 110, "ES": 89, "EG": 4, "BR": 86, "SE": 17, "BG": 5, "IL": 4, "AR": 16, "HU": 10, "PT": 13, "TH": 11, "ZM": 3, "LU": 7, "GR": 24, "SA": 49, "PK": 3, "AE": 33, "MX": 26, "MZ": 9, "JP": 10, "CN": 4, "MT": 5, "BT": 6, "CL": 3, "CO": 29, "RO": 11, "PL": 10, "IS": 3, "IR": 7, "NO": 5, "LB": 6, "nogeo": 27}}